Workbook

Sheet Medicine Master Table
A1: ISLAMIYA PHARMACY
A2: Medicine ID | B2: Medicine Name | C2: Generic Name | D2: Dosage Form | E2: Indication | F2: Cost Price | G2: Pcs per Box | H2: Cost Per Pc | I2: Unit Price | J2: Total Received | K2: Total Sold | L2: Current Stock | M2: Min Stock | N2: Expiry Date | O2: Stock Status | P2: Total Profit | Q2: Lead Time | R2: Annual Consumption Value | S2: Cumulative % | T2: ABC Class
A3: AL-001 | B3: Fenadin 120mg | C3: Fexofenadine | D3: Tablet | E3: Allergy / Antihistamine | F3: 396.23 | G3: 50 | H3: =Table1[[#This Row],[Cost Price]]/Table1[[#This Row],[Pcs per Box]] -> 7.9246 | I3: 9 | J3: =SUMIF('Stock In'!C:C, Table1[[#This Row],[Medicine ID]], 'Stock In'!E:E) * Table1[[#This Row],[Pcs per Box]] -> 400 | K3: =SUMIF('Sales Log Table'!C:C, Table1[[#This Row],[Medicine ID]], 'Sales Log Table'!E:E) -> 0 | L3: =Table1[[#This Row],[Total Received]] - Table1[[#This Row],[Total Sold]] -> 400 | M3: 50 | N3: 46563 | O3: =IF(Table1[[#This Row],[Current Stock]] <= Table1[[#This Row],[Min Stock]], "REORDER NOW", "Good") -> Good | P3: =(Table1[[#This Row],[Unit Price]] - Table1[[#This Row],[Cost Per Pc]]) * Table1[[#This Row],[Total Sold]] -> 0 | R3: =(Table1[[#This Row],[Total Received]] / Table1[[#This Row],[Pcs per Box]]) * Table1[[#This Row],[Cost Price]] -> 3169.84 | S3: =SUM($R$3:Table1[[#This Row],[Annual Consumption Value]]) / SUM(Table1[Annual Consumption Value]) -> 0.011639752 | T3: =IF(Table1[[#This Row],[Cumulative %]]<=0.8, "A", IF(Table1[[#This Row],[Cumulative %]]<=0.95, "B", "C")) -> A
A4: AL-002 | B4: Fenadin 180mg | C4: Fexofenadine | D4: Tablet | E4: Allergy / Antihistamine | F4: =(Table1[[#This Row],[Unit Price]] * 0.9) * Table1[[#This Row],[Pcs per Box]] -> 180 | G4: 20 | H4: =Table1[[#This Row],[Cost Price]]/Table1[[#This Row],[Pcs per Box]] -> 9 | I4: 10 | J4: =SUMIF('Stock In'!C:C, Table1[[#This Row],[Medicine ID]], 'Stock In'!E:E) * Table1[[#This Row],[Pcs per Box]] -> 100 | K4: =SUMIF('Sales Log Table'!C:C, Table1[[#This Row],[Medicine ID]], 'Sales Log Table'!E:E) -> 0 | L4: =Table1[[#This Row],[Total Received]] - Table1[[#This Row],[Total Sold]] -> 100 | M4: 60 | N4: 46563 | O4: =IF(Table1[[#This Row],[Current Stock]] <= Table1[[#This Row],[Min Stock]], "REORDER NOW", "Good") -> Good | P4: =(Table1[[#This Row],[Unit Price]] - Table1[[#This Row],[Cost Per Pc]]) * Table1[[#This Row],[Total Sold]] -> 0 | R4: =(Table1[[#This Row],[Total Received]] / Table1[[#This Row],[Pcs per Box]]) * Table1[[#This Row],[Cost Price]] -> 900 | S4: =SUM($R$3:Table1[[#This Row],[Annual Consumption Value]]) / SUM(Table1[Annual Consumption Value]) -> 0.01494458 | T4: =IF(Table1[[#This Row],[Cumulative %]]<=0.8, "A", IF(Table1[[#This Row],[Cumulative %]]<=0.95, "B", "C")) -> A
A5: AL-003 | B5: Fexo 120mg | C5: Fexofenadine | D5: Tablet | E5: Allergy / Antihistamine | F5: =(Table1[[#This Row],[Unit Price]] * 0.9) * Table1[[#This Row],[Pcs per Box]] -> 405 | G5: 50 | H5: =Table1[[#This Row],[Cost Price]]/Table1[[#This Row],[Pcs per Box]] -> 8.1 | I5: 9 | J5: =SUMIF('Stock In'!C:C, Table1[[#This Row],[Medicine ID]], 'Stock In'!E:E) * Table1[[#This Row],[Pcs per Box]] -> 150 | K5: =SUMIF('Sales Log Table'!C:C, Table1[[#This Row],[Medicine ID]], 'Sales Log Table'!E:E) -> 0 | L5: =Table1[[#This Row],[Total Received]] - Table1[[#This Row],[Total Sold]] -> 150 | M5: 50 | N5: 46563 | O5: =IF(Table1[[#This Row],[Current Stock]] <= Table1[[#This Row],[Min Stock]], "REORDER NOW", "Good") -> Good | P5: =(Table1[[#This Row],[Unit Price]] - Table1[[#This Row],[Cost Per Pc]]) * Table1[[#This Row],[Total Sold]] -> 0 | R5: =(Table1[[#This Row],[Total Received]] / Table1[[#This Row],[Pcs per Box]]) * Table1[[#This Row],[Cost Price]] -> 1215 | S5: =SUM($R$3:Table1[[#This Row],[Annual Consumption Value]]) / SUM(Table1[Annual Consumption Value]) -> 0.019406098 | T5: =IF(Table1[[#This Row],[Cumulative %]]<=0.8, "A", IF(Table1[[#This Row],[Cumulative %]]<=0.95, "B", "C")) -> A
A6: AL-004 | B6: Fexo 180mg | C6: Fexofenadine | D6: Tablet | E6: Allergy / Antihistamine | F6: =(Table1[[#This Row],[Unit Price]] * 0.9) * Table1[[#This Row],[Pcs per Box]] -> 324 | G6: 30 | H6: =Table1[[#This Row],[Cost Price]]/Table1[[#This Row],[Pcs per Box]] -> 10.8 | I6: 12 | J6: =SUMIF('Stock In'!C:C, Table1[[#This Row],[Medicine ID]], 'Stock In'!E:E) * Table1[[#This Row],[Pcs per Box]] -> 60 | K6: =SUMIF('Sales Log Table'!C:C, Table1[[#This Row],[Medicine ID]], 'Sales Log Table'!E:E) -> 0 | L6: =Table1[[#This Row],[Total Received]] - Table1[[#This Row],[Total Sold]] -> 60 | M6: 30 | N6: 46563 | O6: =IF(Table1[[#This Row],[Current Stock]] <= Table1[[#This Row],[Min Stock]], "REORDER NOW", "Good") -> Good | P6: =(Table1[[#This Row],[Unit Price]] - Table1[[#This Row],[Cost Per Pc]]) * Table1[[#This Row],[Total Sold]] -> 0 | R6: =(Table1[[#This Row],[Total Received]] / Table1[[#This Row],[Pcs per Box]]) * Table1[[#This Row],[Cost Price]] -> 648 | S6: =SUM($R$3:Table1[[#This Row],[Annual Consumption Value]]) / SUM(Table1[Annual Consumption Value]) -> 0.021785574 | T6: =IF(Table1[[#This Row],[Cumulative %]]<=0.8, "A", IF(Table1[[#This Row],[Cumulative %]]<=0.95, "B", "C")) -> A
A7: AL-005 | B7: Alatrol | C7: Cetrizine | D7: Tablet | E7: Allergy / Antihistamine | F7: =(Table1[[#This Row],[Unit Price]] * 0.9) * Table1[[#This Row],[Pcs per Box]] -> 405 | G7: 150 | H7: =Table1[[#This Row],[Cost Price]]/Table1[[#This Row],[Pcs per Box]] -> 2.7 | I7: 3 | J7: =SUMIF('Stock In'!C:C, Table1[[#This Row],[Medicine ID]], 'Stock In'!E:E) * Table1[[#This Row],[Pcs per Box]] -> 300 | K7: =SUMIF('Sales Log Table'!C:C, Table1[[#This Row],[Medicine ID]], 'Sales Log Table'!E:E) -> 10 | L7: =Table1[[#This Row],[Total Received]] - Table1[[#This Row],[Total Sold]] -> 290 | M7: 40 | N7: 46563 | O7: =IF(Table1[[#This Row],[Current Stock]] <= Table1[[#This Row],[Min Stock]], "REORDER NOW", "Good") -> Good | P7: =(Table1[[#This Row],[Unit Price]] - Table1[[#This Row],[Cost Per Pc]]) * Table1[[#This Row],[Total Sold]] -> 3 | R7: =(Table1[[#This Row],[Total Received]] / Table1[[#This Row],[Pcs per Box]]) * Table1[[#This Row],[Cost Price]] -> 810 | S7: =SUM($R$3:Table1[[#This Row],[Annual Consumption Value]]) / SUM(Table1[Annual Consumption Value]) -> 0.02475992 | T7: =IF(Table1[[#This Row],[Cumulative %]]<=0.8, "A", IF(Table1[[#This Row],[Cumulative %]]<=0.95, "B", "C")) -> A
A8: AL-006 | B8: Alat | C8: Cetrizine | D8: Tablet | E8: Allergy / Antihistamine | F8: =(Table1[[#This Row],[Unit Price]] * 0.9) * Table1[[#This Row],[Pcs per Box]] -> 225 | G8: 100 | H8: =Table1[[#This Row],[Cost Price]]/Table1[[#This Row],[Pcs per Box]] -> 2.25 | I8: 2.5 | J8: =SUMIF('Stock In'!C:C, Table1[[#This Row],[Medicine ID]], 'Stock In'!E:E) * Table1[[#This Row],[Pcs per Box]] -> 200 | K8: =SUMIF('Sales Log Table'!C:C, Table1[[#This Row],[Medicine ID]], 'Sales Log Table'!E:E) -> 0 | L8: =Table1[[#This Row],[Total Received]] - Table1[[#This Row],[Total Sold]] -> 200 | M8: 87 | N8: 46563 | O8: =IF(Table1[[#This Row],[Current Stock]] <= Table1[[#This Row],[Min Stock]], "REORDER NOW", "Good") -> Good | P8: =(Table1[[#This Row],[Unit Price]] - Table1[[#This Row],[Cost Per Pc]]) * Table1[[#This Row],[Total Sold]] -> 0 | R8: =(Table1[[#This Row],[Total Received]] / Table1[[#This Row],[Pcs per Box]]) * Table1[[#This Row],[Cost Price]] -> 450 | S8: =SUM($R$3:Table1[[#This Row],[Annual Consumption Value]]) / SUM(Table1[Annual Consumption Value]) -> 0.026412334 | T8: =IF(Table1[[#This Row],[Cumulative %]]<=0.8, "A", IF(Table1[[#This Row],[Cumulative %]]<=0.95, "B", "C")) -> A
A9: AL-007 | B9: Atrizin | C9: Cetrizine | D9: Tablet | E9: Allergy / Antihistamine | F9: =(Table1[[#This Row],[Unit Price]] * 0.9) * Table1[[#This Row],[Pcs per Box]] -> 405 | G9: 150 | H9: =Table1[[#This Row],[Cost Price]]/Table1[[#This Row],[Pcs per Box]] -> 2.7 | I9: 3 | J9: =SUMIF('Stock In'!C:C, Table1[[#This Row],[Medicine ID]], 'Stock In'!E:E) * Table1[[#This Row],[Pcs per Box]] -> 600 | K9: =SUMIF('Sales Log Table'!C:C, Table1[[#This Row],[Medicine ID]], 'Sales Log Table'!E:E) -> 0 | L9: =Table1[[#This Row],[Total Received]] - Table1[[#This Row],[Total Sold]] -> 600 | M9: 67 | N9: 46563 | O9: =IF(Table1[[#This Row],[Current Stock]] <= Table1[[#This Row],[Min Stock]], "REORDER NOW", "Good") -> Good | P9: =(Table1[[#This Row],[Unit Price]] - Table1[[#This Row],[Cost Per Pc]]) * Table1[[#This Row],[Total Sold]] -> 0 | R9: =(Table1[[#This Row],[Total Received]] / Table1[[#This Row],[Pcs per Box]]) * Table1[[#This Row],[Cost Price]] -> 1620 | S9: =SUM($R$3:Table1[[#This Row],[Annual Consumption Value]]) / SUM(Table1[Annual Consumption Value]) -> 0.032361025 | T9: =IF(Table1[[#This Row],[Cumulative %]]<=0.8, "A", IF(Table1[[#This Row],[Cumulative %]]<=0.95, "B", "C")) -> A
A10: AL-008 | B10: Atrizin 15ml | C10: Cetrizine | D10: PD | E10: Allergy / Antihistamine | F10: =(Table1[[#This Row],[Unit Price]] * 0.9) * Table1[[#This Row],[Pcs per Box]] -> 22.5 | G10: 1 | H10: =Table1[[#This Row],[Cost Price]]/Table1[[#This Row],[Pcs per Box]] -> 22.5 | I10: 25 | J10: =SUMIF('Stock In'!C:C, Table1[[#This Row],[Medicine ID]], 'Stock In'!E:E) * Table1[[#This Row],[Pcs per Box]] -> 10 | K10: =SUMIF('Sales Log Table'!C:C, Table1[[#This Row],[Medicine ID]], 'Sales Log Table'!E:E) -> 0 | L10: =Table1[[#This Row],[Total Received]] - Table1[[#This Row],[Total Sold]] -> 10 | M10: 3 | N10: 46563 | O10: =IF(Table1[[#This Row],[Current Stock]] <= Table1[[#This Row],[Min Stock]], "REORDER NOW", "Good") -> Good | P10: =(Table1[[#This Row],[Unit Price]] - Table1[[#This Row],[Cost Per Pc]]) * Table1[[#This Row],[Total Sold]] -> 0 | R10: =(Table1[[#This Row],[Total Received]] / Table1[[#This Row],[Pcs per Box]]) * Table1[[#This Row],[Cost Price]] -> 225 | S10: =SUM($R$3:Table1[[#This Row],[Annual Consumption Value]]) / SUM(Table1[Annual Consumption Value]) -> 0.033187232 | T10: =IF(Table1[[#This Row],[Cumulative %]]<=0.8, "A", IF(Table1[[#This Row],[Cumulative %]]<=0.95, "B", "C")) -> A
A11: AL-009 | B11: Alatrol | C11: Cetrizine | D11: PD | E11: Allergy / Antihistamine | F11: =(Table1[[#This Row],[Unit Price]] * 0.9) * Table1[[#This Row],[Pcs per Box]] -> 25.2 | G11: 1 | H11: =Table1[[#This Row],[Cost Price]]/Table1[[#This Row],[Pcs per Box]] -> 25.2 | I11: 28 | J11: =SUMIF('Stock In'!C:C, Table1[[#This Row],[Medicine ID]], 'Stock In'!E:E) * Table1[[#This Row],[Pcs per Box]] -> 10 | K11: =SUMIF('Sales Log Table'!C:C, Table1[[#This Row],[Medicine ID]], 'Sales Log Table'!E:E) -> 0 | L11: =Table1[[#This Row],[Total Received]] - Table1[[#This Row],[Total Sold]] -> 10 | M11: 5 | N11: 46563 | O11: =IF(Table1[[#This Row],[Current Stock]] <= Table1[[#This Row],[Min Stock]], "REORDER NOW", "Good") -> Good | P11: =(Table1[[#This Row],[Unit Price]] - Table1[[#This Row],[Cost Per Pc]]) * Table1[[#This Row],[Total Sold]] -> 0 | R11: =(Table1[[#This Row],[Total Received]] / Table1[[#This Row],[Pcs per Box]]) * Table1[[#This Row],[Cost Price]] -> 252 | S11: =SUM($R$3:Table1[[#This Row],[Annual Consumption Value]]) / SUM(Table1[Annual Consumption Value]) -> 0.034112584 | T11: =IF(Table1[[#This Row],[Cumulative %]]<=0.8, "A", IF(Table1[[#This Row],[Cumulative %]]<=0.95, "B", "C")) -> A
A12: AL-010 | B12: Alatrol 60ml | C12: Cetrizine | D12: Syrup | E12: Allergy / Antihistamine | F12: =(Table1[[#This Row],[Unit Price]] * 0.9) * Table1[[#This Row],[Pcs per Box]] -> 31.5 | G12: 1 | H12: =Table1[[#This Row],[Cost Price]]/Table1[[#This Row],[Pcs per Box]] -> 31.5 | I12: 35 | J12: =SUMIF('Stock In'!C:C, Table1[[#This Row],[Medicine ID]], 'Stock In'!E:E) * Table1[[#This Row],[Pcs per Box]] -> 5 | K12: =SUMIF('Sales Log Table'!C:C, Table1[[#This Row],[Medicine ID]], 'Sales Log Table'!E:E) -> 0 | L12: =Table1[[#This Row],[Total Received]] - Table1[[#This Row],[Total Sold]] -> 5 | M12: 2 | N12: 46563 | O12: =IF(Table1[[#This Row],[Current Stock]] <= Table1[[#This Row],[Min Stock]], "REORDER NOW", "Good") -> Good | P12: =(Table1[[#This Row],[Unit Price]] - Table1[[#This Row],[Cost Per Pc]]) * Table1[[#This Row],[Total Sold]] -> 0 | R12: =(Table1[[#This Row],[Total Received]] / Table1[[#This Row],[Pcs per Box]]) * Table1[[#This Row],[Cost Price]] -> 157.5 | S12: =SUM($R$3:Table1[[#This Row],[Annual Consumption Value]]) / SUM(Table1[Annual Consumption Value]) -> 0.034690929 | T12: =IF(Table1[[#This Row],[Cumulative %]]<=0.8, "A", IF(Table1[[#This Row],[Cumulative %]]<=0.95, "B", "C")) -> A
A13: AL-011 | B13: Bilastin 20mg | C13: Bilastine | D13: Tablet | E13: Allergy / Antihistamine | F13: 422.43 | G13: 30 | H13: =Table1[[#This Row],[Cost Price]]/Table1[[#This Row],[Pcs per Box]] -> 14.081 | I13: 16 | J13: =SUMIF('Stock In'!C:C, Table1[[#This Row],[Medicine ID]], 'Stock In'!E:E) * Table1[[#This Row],[Pcs per Box]] -> 180 | K13: =SUMIF('Sales Log Table'!C:C, Table1[[#This Row],[Medicine ID]], 'Sales Log Table'!E:E) -> 0 | L13: =Table1[[#This Row],[Total Received]] - Table1[[#This Row],[Total Sold]] -> 180 | M13: 30 | N13: 46563 | O13: =IF(Table1[[#This Row],[Current Stock]] <= Table1[[#This Row],[Min Stock]], "REORDER NOW", "Good") -> Good | P13: =(Table1[[#This Row],[Unit Price]] - Table1[[#This Row],[Cost Per Pc]]) * Table1[[#This Row],[Total Sold]] -> 0 | R13: =(Table1[[#This Row],[Total Received]] / Table1[[#This Row],[Pcs per Box]]) * Table1[[#This Row],[Cost Price]] -> 2534.58 | S13: =SUM($R$3:Table1[[#This Row],[Annual Consumption Value]]) / SUM(Table1[Annual Consumption Value]) -> 0.043997986 | T13: =IF(Table1[[#This Row],[Cumulative %]]<=0.8, "A", IF(Table1[[#This Row],[Cumulative %]]<=0.95, "B", "C")) -> A
A14: AL-012 | B14: M-Lucas 10 | C14: Montelukast | D14: Tablet | E14: Asthma / Allergic Rhinitis | F14: 448.83 | G14: 30 | H14: =Table1[[#This Row],[Cost Price]]/Table1[[#This Row],[Pcs per Box]] -> 14.961 | I14: 17 | J14: =SUMIF('Stock In'!C:C, Table1[[#This Row],[Medicine ID]], 'Stock In'!E:E) * Table1[[#This Row],[Pcs per Box]] -> 450 | K14: =SUMIF('Sales Log Table'!C:C, Table1[[#This Row],[Medicine ID]], 'Sales Log Table'!E:E) -> 0 | L14: =Table1[[#This Row],[Total Received]] - Table1[[#This Row],[Total Sold]] -> 450 | M14: 30 | N14: 46563 | O14: =IF(Table1[[#This Row],[Current Stock]] <= Table1[[#This Row],[Min Stock]], "REORDER NOW", "Good") -> Good | P14: =(Table1[[#This Row],[Unit Price]] - Table1[[#This Row],[Cost Per Pc]]) * Table1[[#This Row],[Total Sold]] -> 0 | R14: =(Table1[[#This Row],[Total Received]] / Table1[[#This Row],[Pcs per Box]]) * Table1[[#This Row],[Cost Price]] -> 6732.45 | S14: =SUM($R$3:Table1[[#This Row],[Annual Consumption Value]]) / SUM(Table1[Annual Consumption Value]) -> 0.068719753 | T14: =IF(Table1[[#This Row],[Cumulative %]]<=0.8, "A", IF(Table1[[#This Row],[Cumulative %]]<=0.95, "B", "C")) -> A
A15: AL-013 | B15: Lumona 10 | C15: Montelukast | D15: Tablet | E15: Asthma / Allergic Rhinitis | F15: 443.56 | G15: 42 | H15: =Table1[[#This Row],[Cost Price]]/Table1[[#This Row],[Pcs per Box]] -> 10.560952 | I15: 12 | J15: =SUMIF('Stock In'!C:C, Table1[[#This Row],[Medicine ID]], 'Stock In'!E:E) * Table1[[#This Row],[Pcs per Box]] -> 84 | K15: =SUMIF('Sales Log Table'!C:C, Table1[[#This Row],[Medicine ID]], 'Sales Log Table'!E:E) -> 0 | L15: =Table1[[#This Row],[Total Received]] - Table1[[#This Row],[Total Sold]] -> 84 | M15: 42 | N15: 46563 | O15: =IF(Table1[[#This Row],[Current Stock]] <= Table1[[#This Row],[Min Stock]], "REORDER NOW", "Good") -> Good | P15: =(Table1[[#This Row],[Unit Price]] - Table1[[#This Row],[Cost Per Pc]]) * Table1[[#This Row],[Total Sold]] -> 0 | R15: =(Table1[[#This Row],[Total Received]] / Table1[[#This Row],[Pcs per Box]]) * Table1[[#This Row],[Cost Price]] -> 887.12 | S15: =SUM($R$3:Table1[[#This Row],[Annual Consumption Value]]) / SUM(Table1[Annual Consumption Value]) -> 0.071977286 | T15: =IF(Table1[[#This Row],[Cumulative %]]<=0.8, "A", IF(Table1[[#This Row],[Cumulative %]]<=0.95, "B", "C")) -> A
A16: AL-014 | B16: Superitra 65mg | C16: Itraconazole | D16: Capsule | E16: Antifungal | F16: 528.04 | G16: 30 | H16: =Table1[[#This Row],[Cost Price]]/Table1[[#This Row],[Pcs per Box]] -> 17.601333 | I16: 20 | J16: =SUMIF('Stock In'!C:C, Table1[[#This Row],[Medicine ID]], 'Stock In'!E:E) * Table1[[#This Row],[Pcs per Box]] -> 150 | K16: =SUMIF('Sales Log Table'!C:C, Table1[[#This Row],[Medicine ID]], 'Sales Log Table'!E:E) -> 0 | L16: =Table1[[#This Row],[Total Received]] - Table1[[#This Row],[Total Sold]] -> 150 | M16: 30 | N16: 46563 | O16: =IF(Table1[[#This Row],[Current Stock]] <= Table1[[#This Row],[Min Stock]], "REORDER NOW", "Good") -> Good | P16: =(Table1[[#This Row],[Unit Price]] - Table1[[#This Row],[Cost Per Pc]]) * Table1[[#This Row],[Total Sold]] -> 0 | R16: =(Table1[[#This Row],[Total Received]] / Table1[[#This Row],[Pcs per Box]]) * Table1[[#This Row],[Cost Price]] -> 2640.2 | S16: =SUM($R$3:Table1[[#This Row],[Annual Consumption Value]]) / SUM(Table1[Annual Consumption Value]) -> 0.081672183 | T16: =IF(Table1[[#This Row],[Cumulative %]]<=0.8, "A", IF(Table1[[#This Row],[Cumulative %]]<=0.95, "B", "C")) -> A
A17: AL-015 | B17: Ebatin | C17: Ebastine | D17: Tablet | E17: Allergy / Antihistamine | F17: 528.04 | G17: 60 | H17: =Table1[[#This Row],[Cost Price]]/Table1[[#This Row],[Pcs per Box]] -> 8.8006667 | I17: 10 | J17: =SUMIF('Stock In'!C:C, Table1[[#This Row],[Medicine ID]], 'Stock In'!E:E) * Table1[[#This Row],[Pcs per Box]] -> 300 | K17: =SUMIF('Sales Log Table'!C:C, Table1[[#This Row],[Medicine ID]], 'Sales Log Table'!E:E) -> 10 | L17: =Table1[[#This Row],[Total Received]] - Table1[[#This Row],[Total Sold]] -> 290 | M17: 60 | N17: 46563 | O17: =IF(Table1[[#This Row],[Current Stock]] <= Table1[[#This Row],[Min Stock]], "REORDER NOW", "Good") -> Good | P17: =(Table1[[#This Row],[Unit Price]] - Table1[[#This Row],[Cost Per Pc]]) * Table1[[#This Row],[Total Sold]] -> 11.993333 | R17: =(Table1[[#This Row],[Total Received]] / Table1[[#This Row],[Pcs per Box]]) * Table1[[#This Row],[Cost Price]] -> 2640.2 | S17: =SUM($R$3:Table1[[#This Row],[Annual Consumption Value]]) / SUM(Table1[Annual Consumption Value]) -> 0.09136708 | T17: =IF(Table1[[#This Row],[Cumulative %]]<=0.8, "A", IF(Table1[[#This Row],[Cumulative %]]<=0.95, "B", "C")) -> A
A18: AL-016 | B18: Bilbest 20mg | C18: Bilastine | D18: Tablet | E18: Allergy / Antihistamine | F18: 396.03 | G18: 30 | H18: =Table1[[#This Row],[Cost Price]]/Table1[[#This Row],[Pcs per Box]] -> 13.201 | I18: 15 | J18: =SUMIF('Stock In'!C:C, Table1[[#This Row],[Medicine ID]], 'Stock In'!E:E) * Table1[[#This Row],[Pcs per Box]] -> 600 | K18: =SUMIF('Sales Log Table'!C:C, Table1[[#This Row],[Medicine ID]], 'Sales Log Table'!E:E) -> 10 | L18: =Table1[[#This Row],[Total Received]] - Table1[[#This Row],[Total Sold]] -> 590 | M18: 50 | O18: =IF(Table1[[#This Row],[Current Stock]] <= Table1[[#This Row],[Min Stock]], "REORDER NOW", "Good") -> Good | P18: =(Table1[[#This Row],[Unit Price]] - Table1[[#This Row],[Cost Per Pc]]) * Table1[[#This Row],[Total Sold]] -> 17.99 | R18: =(Table1[[#This Row],[Total Received]] / Table1[[#This Row],[Pcs per Box]]) * Table1[[#This Row],[Cost Price]] -> 7920.6 | S18: =SUM($R$3:Table1[[#This Row],[Annual Consumption Value]]) / SUM(Table1[Annual Consumption Value]) -> 0.12045177 | T18: =IF(Table1[[#This Row],[Cumulative %]]<=0.8, "A", IF(Table1[[#This Row],[Cumulative %]]<=0.95, "B", "C")) -> A
A19: AL-017 | B19: Dexpoten Plus 100ml | C19: Dextromethorphan + Phenylephrine + Triprolidine | D19: Syrup | E19: Cough / Sneezing | F19: 96.83 | G19: 1 | H19: =Table1[[#This Row],[Cost Price]]/Table1[[#This Row],[Pcs per Box]] -> 96.83 | I19: 110 | J19: =SUMIF('Stock In'!C:C, Table1[[#This Row],[Medicine ID]], 'Stock In'!E:E) * Table1[[#This Row],[Pcs per Box]] -> 24 | K19: =SUMIF('Sales Log Table'!C:C, Table1[[#This Row],[Medicine ID]], 'Sales Log Table'!E:E) -> 0 | L19: =Table1[[#This Row],[Total Received]] - Table1[[#This Row],[Total Sold]] -> 24 | M19: 1 | N19: 46563 | O19: =IF(Table1[[#This Row],[Current Stock]] <= Table1[[#This Row],[Min Stock]], "REORDER NOW", "Good") -> Good | P19: =(Table1[[#This Row],[Unit Price]] - Table1[[#This Row],[Cost Per Pc]]) * Table1[[#This Row],[Total Sold]] -> 0 | R19: =(Table1[[#This Row],[Total Received]] / Table1[[#This Row],[Pcs per Box]]) * Table1[[#This Row],[Cost Price]] -> 2323.92 | S19: =SUM($R$3:Table1[[#This Row],[Annual Consumption Value]]) / SUM(Table1[Annual Consumption Value]) -> 0.12898528 | T19: =IF(Table1[[#This Row],[Cumulative %]]<=0.8, "A", IF(Table1[[#This Row],[Cumulative %]]<=0.95, "B", "C")) -> A
A20: AL-018 | B20: Itrakill SB 65mg | C20: Itraconazole | D20: Capsule | E20: Antifungal | F20: 528 | G20: 30 | H20: =Table1[[#This Row],[Cost Price]]/Table1[[#This Row],[Pcs per Box]] -> 17.6 | I20: 20 | J20: =SUMIF('Stock In'!C:C, Table1[[#This Row],[Medicine ID]], 'Stock In'!E:E) * Table1[[#This Row],[Pcs per Box]] -> 150 | K20: =SUMIF('Sales Log Table'!C:C, Table1[[#This Row],[Medicine ID]], 'Sales Log Table'!E:E) -> 0 | L20: =Table1[[#This Row],[Total Received]] - Table1[[#This Row],[Total Sold]] -> 150 | M20: 30 | N20: 46563 | O20: =IF(Table1[[#This Row],[Current Stock]] <= Table1[[#This Row],[Min Stock]], "REORDER NOW", "Good") -> Good | P20: =(Table1[[#This Row],[Unit Price]] - Table1[[#This Row],[Cost Per Pc]]) * Table1[[#This Row],[Total Sold]] -> 0 | R20: =(Table1[[#This Row],[Total Received]] / Table1[[#This Row],[Pcs per Box]]) * Table1[[#This Row],[Cost Price]] -> 2640 | S20: =SUM($R$3:Table1[[#This Row],[Annual Consumption Value]]) / SUM(Table1[Annual Consumption Value]) -> 0.13867944 | T20: =IF(Table1[[#This Row],[Cumulative %]]<=0.8, "A", IF(Table1[[#This Row],[Cumulative %]]<=0.95, "B", "C")) -> A
A21: AL-019 | B21: Mebolin 50mg | C21: Mebhydrolin Napadisylate | D21: Tablet | E21: Allergy | F21: 264 | G21: 100 | H21: =Table1[[#This Row],[Cost Price]]/Table1[[#This Row],[Pcs per Box]] -> 2.64 | I21: 3 | J21: =SUMIF('Stock In'!C:C, Table1[[#This Row],[Medicine ID]], 'Stock In'!E:E) * Table1[[#This Row],[Pcs per Box]] -> 500 | K21: =SUMIF('Sales Log Table'!C:C, Table1[[#This Row],[Medicine ID]], 'Sales Log Table'!E:E) -> 0 | L21: =Table1[[#This Row],[Total Received]] - Table1[[#This Row],[Total Sold]] -> 500 | M21: 100 | N21: 46563 | O21: =IF(Table1[[#This Row],[Current Stock]] <= Table1[[#This Row],[Min Stock]], "REORDER NOW", "Good") -> Good | P21: =(Table1[[#This Row],[Unit Price]] - Table1[[#This Row],[Cost Per Pc]]) * Table1[[#This Row],[Total Sold]] -> 0 | R21: =(Table1[[#This Row],[Total Received]] / Table1[[#This Row],[Pcs per Box]]) * Table1[[#This Row],[Cost Price]] -> 1320 | S21: =SUM($R$3:Table1[[#This Row],[Annual Consumption Value]]) / SUM(Table1[Annual Consumption Value]) -> 0.14352652 | T21: =IF(Table1[[#This Row],[Cumulative %]]<=0.8, "A", IF(Table1[[#This Row],[Cumulative %]]<=0.95, "B", "C")) -> A
A22: AL-020 | B22: Telfadin 180mg | C22: Fexofenadine | D22: Tablet | E22: Allergy / Antihistamine | F22: 176.02 | G22: 20 | H22: =Table1[[#This Row],[Cost Price]]/Table1[[#This Row],[Pcs per Box]] -> 8.801 | I22: 10 | J22: =SUMIF('Stock In'!C:C, Table1[[#This Row],[Medicine ID]], 'Stock In'!E:E) * Table1[[#This Row],[Pcs per Box]] -> 200 | K22: =SUMIF('Sales Log Table'!C:C, Table1[[#This Row],[Medicine ID]], 'Sales Log Table'!E:E) -> 0 | L22: =Table1[[#This Row],[Total Received]] - Table1[[#This Row],[Total Sold]] -> 200 | O22: =IF(Table1[[#This Row],[Current Stock]] <= Table1[[#This Row],[Min Stock]], "REORDER NOW", "Good") -> Good | P22: =(Table1[[#This Row],[Unit Price]] - Table1[[#This Row],[Cost Per Pc]]) * Table1[[#This Row],[Total Sold]] -> 0 | R22: =(Table1[[#This Row],[Total Received]] / Table1[[#This Row],[Pcs per Box]]) * Table1[[#This Row],[Cost Price]] -> 1760.2 | S22: =SUM($R$3:Table1[[#This Row],[Annual Consumption Value]]) / SUM(Table1[Annual Consumption Value]) -> 0.14999003 | T22: =IF(Table1[[#This Row],[Cumulative %]]<=0.8, "A", IF(Table1[[#This Row],[Cumulative %]]<=0.95, "B", "C")) -> A
A23: AN-001 | B23: Flubac 250 | C23: Flucloxacillin Sodium | D23: Capsule | E23: Antibiotic | F23: =(Table1[[#This Row],[Unit Price]] * 0.9) * Table1[[#This Row],[Pcs per Box]] -> 374.4 | G23: 52 | H23: =Table1[[#This Row],[Cost Price]]/Table1[[#This Row],[Pcs per Box]] -> 7.2 | I23: 8 | J23: =SUMIF('Stock In'!C:C, Table1[[#This Row],[Medicine ID]], 'Stock In'!E:E) * Table1[[#This Row],[Pcs per Box]] -> 52 | K23: =SUMIF('Sales Log Table'!C:C, Table1[[#This Row],[Medicine ID]], 'Sales Log Table'!E:E) -> 0 | L23: =Table1[[#This Row],[Total Received]] - Table1[[#This Row],[Total Sold]] -> 52 | M23: 20 | N23: 46563 | O23: =IF(Table1[[#This Row],[Current Stock]] <= Table1[[#This Row],[Min Stock]], "REORDER NOW", "Good") -> Good | P23: =(Table1[[#This Row],[Unit Price]] - Table1[[#This Row],[Cost Per Pc]]) * Table1[[#This Row],[Total Sold]] -> 0 | R23: =(Table1[[#This Row],[Total Received]] / Table1[[#This Row],[Pcs per Box]]) * Table1[[#This Row],[Cost Price]] -> 374.4 | S23: =SUM($R$3:Table1[[#This Row],[Annual Consumption Value]]) / SUM(Table1[Annual Consumption Value]) -> 0.15136484 | T23: =IF(Table1[[#This Row],[Cumulative %]]<=0.8, "A", IF(Table1[[#This Row],[Cumulative %]]<=0.95, "B", "C")) -> A
A24: AN-002 | B24: Flubac 500 | C24: Flucloxacillin Sodium | D24: Capsule | E24: Antibiotic | F24: =(Table1[[#This Row],[Unit Price]] * 0.9) * Table1[[#This Row],[Pcs per Box]] -> 403.2 | G24: 32 | H24: =Table1[[#This Row],[Cost Price]]/Table1[[#This Row],[Pcs per Box]] -> 12.6 | I24: 14 | J24: =SUMIF('Stock In'!C:C, Table1[[#This Row],[Medicine ID]], 'Stock In'!E:E) * Table1[[#This Row],[Pcs per Box]] -> 128 | K24: =SUMIF('Sales Log Table'!C:C, Table1[[#This Row],[Medicine ID]], 'Sales Log Table'!E:E) -> 0 | L24: =Table1[[#This Row],[Total Received]] - Table1[[#This Row],[Total Sold]] -> 128 | M24: 80 | N24: 46563 | O24: =IF(Table1[[#This Row],[Current Stock]] <= Table1[[#This Row],[Min Stock]], "REORDER NOW", "Good") -> Good | P24: =(Table1[[#This Row],[Unit Price]] - Table1[[#This Row],[Cost Per Pc]]) * Table1[[#This Row],[Total Sold]] -> 0 | R24: =(Table1[[#This Row],[Total Received]] / Table1[[#This Row],[Pcs per Box]]) * Table1[[#This Row],[Cost Price]] -> 1612.8 | S24: =SUM($R$3:Table1[[#This Row],[Annual Consumption Value]]) / SUM(Table1[Annual Consumption Value]) -> 0.15728709 | T24: =IF(Table1[[#This Row],[Cumulative %]]<=0.8, "A", IF(Table1[[#This Row],[Cumulative %]]<=0.95, "B", "C")) -> A
A25: AN-003 | B25: Flucloxin 250 | C25: Flucloxacillin Sodium | D25: Capsule | E25: Antibiotic | F25: =(Table1[[#This Row],[Unit Price]] * 0.9) * Table1[[#This Row],[Pcs per Box]] -> 519.3 | G25: 100 | H25: =Table1[[#This Row],[Cost Price]]/Table1[[#This Row],[Pcs per Box]] -> 5.193 | I25: 5.77 | J25: =SUMIF('Stock In'!C:C, Table1[[#This Row],[Medicine ID]], 'Stock In'!E:E) * Table1[[#This Row],[Pcs per Box]] -> 500 | K25: =SUMIF('Sales Log Table'!C:C, Table1[[#This Row],[Medicine ID]], 'Sales Log Table'!E:E) -> 0 | L25: =Table1[[#This Row],[Total Received]] - Table1[[#This Row],[Total Sold]] -> 500 | M25: 30 | N25: 46563 | O25: =IF(Table1[[#This Row],[Current Stock]] <= Table1[[#This Row],[Min Stock]], "REORDER NOW", "Good") -> Good | P25: =(Table1[[#This Row],[Unit Price]] - Table1[[#This Row],[Cost Per Pc]]) * Table1[[#This Row],[Total Sold]] -> 0 | R25: =(Table1[[#This Row],[Total Received]] / Table1[[#This Row],[Pcs per Box]]) * Table1[[#This Row],[Cost Price]] -> 2596.5 | S25: =SUM($R$3:Table1[[#This Row],[Annual Consumption Value]]) / SUM(Table1[Annual Consumption Value]) -> 0.16682152 | T25: =IF(Table1[[#This Row],[Cumulative %]]<=0.8, "A", IF(Table1[[#This Row],[Cumulative %]]<=0.95, "B", "C")) -> A
A26: AN-004 | B26: Flucloxin 500 | C26: Flucloxacillin Sodium | D26: Capsule | E26: Antibiotic | F26: =(Table1[[#This Row],[Unit Price]] * 0.9) * Table1[[#This Row],[Pcs per Box]] -> 378 | G26: 40 | H26: =Table1[[#This Row],[Cost Price]]/Table1[[#This Row],[Pcs per Box]] -> 9.45 | I26: 10.5 | J26: =SUMIF('Stock In'!C:C, Table1[[#This Row],[Medicine ID]], 'Stock In'!E:E) * Table1[[#This Row],[Pcs per Box]] -> 200 | K26: =SUMIF('Sales Log Table'!C:C, Table1[[#This Row],[Medicine ID]], 'Sales Log Table'!E:E) -> 0 | L26: =Table1[[#This Row],[Total Received]] - Table1[[#This Row],[Total Sold]] -> 200 | M26: 80 | N26: 46563 | O26: =IF(Table1[[#This Row],[Current Stock]] <= Table1[[#This Row],[Min Stock]], "REORDER NOW", "Good") -> Good | P26: =(Table1[[#This Row],[Unit Price]] - Table1[[#This Row],[Cost Per Pc]]) * Table1[[#This Row],[Total Sold]] -> 0 | R26: =(Table1[[#This Row],[Total Received]] / Table1[[#This Row],[Pcs per Box]]) * Table1[[#This Row],[Cost Price]] -> 1890 | S26: =SUM($R$3:Table1[[#This Row],[Annual Consumption Value]]) / SUM(Table1[Annual Consumption Value]) -> 0.17376166 | T26: =IF(Table1[[#This Row],[Cumulative %]]<=0.8, "A", IF(Table1[[#This Row],[Cumulative %]]<=0.95, "B", "C")) -> A
A27: AN-005 | B27: Zimax 500 | C27: Azithromycin | D27: Tablet | E27: Antibiotic | F27: =(Table1[[#This Row],[Unit Price]] * 0.9) * Table1[[#This Row],[Pcs per Box]] -> 648 | G27: 18 | H27: =Table1[[#This Row],[Cost Price]]/Table1[[#This Row],[Pcs per Box]] -> 36 | I27: 40 | J27: =SUMIF('Stock In'!C:C, Table1[[#This Row],[Medicine ID]], 'Stock In'!E:E) * Table1[[#This Row],[Pcs per Box]] -> 144 | K27: =SUMIF('Sales Log Table'!C:C, Table1[[#This Row],[Medicine ID]], 'Sales Log Table'!E:E) -> 3 | L27: =Table1[[#This Row],[Total Received]] - Table1[[#This Row],[Total Sold]] -> 141 | M27: 40 | N27: 46563 | O27: =IF(Table1[[#This Row],[Current Stock]] <= Table1[[#This Row],[Min Stock]], "REORDER NOW", "Good") -> Good | P27: =(Table1[[#This Row],[Unit Price]] - Table1[[#This Row],[Cost Per Pc]]) * Table1[[#This Row],[Total Sold]] -> 12 | R27: =(Table1[[#This Row],[Total Received]] / Table1[[#This Row],[Pcs per Box]]) * Table1[[#This Row],[Cost Price]] -> 5184 | S27: =SUM($R$3:Table1[[#This Row],[Annual Consumption Value]]) / SUM(Table1[Annual Consumption Value]) -> 0.19279747 | T27: =IF(Table1[[#This Row],[Cumulative %]]<=0.8, "A", IF(Table1[[#This Row],[Cumulative %]]<=0.95, "B", "C")) -> A
A28: AN-006 | B28: AZ 500 | C28: Azithromycin | D28: Tablet | E28: Antibiotic | F28: =(Table1[[#This Row],[Unit Price]] * 0.9) * Table1[[#This Row],[Pcs per Box]] -> 594 | G28: 12 | H28: =Table1[[#This Row],[Cost Price]]/Table1[[#This Row],[Pcs per Box]] -> 49.5 | I28: 55 | J28: =SUMIF('Stock In'!C:C, Table1[[#This Row],[Medicine ID]], 'Stock In'!E:E) * Table1[[#This Row],[Pcs per Box]] -> 72 | K28: =SUMIF('Sales Log Table'!C:C, Table1[[#This Row],[Medicine ID]], 'Sales Log Table'!E:E) -> 0 | L28: =Table1[[#This Row],[Total Received]] - Table1[[#This Row],[Total Sold]] -> 72 | M28: 50 | N28: 46563 | O28: =IF(Table1[[#This Row],[Current Stock]] <= Table1[[#This Row],[Min Stock]], "REORDER NOW", "Good") -> Good | P28: =(Table1[[#This Row],[Unit Price]] - Table1[[#This Row],[Cost Per Pc]]) * Table1[[#This Row],[Total Sold]] -> 0 | R28: =(Table1[[#This Row],[Total Received]] / Table1[[#This Row],[Pcs per Box]]) * Table1[[#This Row],[Cost Price]] -> 3564 | S28: =SUM($R$3:Table1[[#This Row],[Annual Consumption Value]]) / SUM(Table1[Annual Consumption Value]) -> 0.20588459 | T28: =IF(Table1[[#This Row],[Cumulative %]]<=0.8, "A", IF(Table1[[#This Row],[Cumulative %]]<=0.95, "B", "C")) -> A
A29: AN-007 | B29: Zithrox 500 | C29: Azithromycin | D29: Tablet | E29: Antibiotic | F29: 422.43 | G29: 12 | H29: =Table1[[#This Row],[Cost Price]]/Table1[[#This Row],[Pcs per Box]] -> 35.2025 | I29: 40 | J29: =SUMIF('Stock In'!C:C, Table1[[#This Row],[Medicine ID]], 'Stock In'!E:E) * Table1[[#This Row],[Pcs per Box]] -> 96 | K29: =SUMIF('Sales Log Table'!C:C, Table1[[#This Row],[Medicine ID]], 'Sales Log Table'!E:E) -> 0 | L29: =Table1[[#This Row],[Total Received]] - Table1[[#This Row],[Total Sold]] -> 96 | M29: 30 | N29: 46563 | O29: =IF(Table1[[#This Row],[Current Stock]] <= Table1[[#This Row],[Min Stock]], "REORDER NOW", "Good") -> Good | P29: =(Table1[[#This Row],[Unit Price]] - Table1[[#This Row],[Cost Per Pc]]) * Table1[[#This Row],[Total Sold]] -> 0 | R29: =(Table1[[#This Row],[Total Received]] / Table1[[#This Row],[Pcs per Box]]) * Table1[[#This Row],[Cost Price]] -> 3379.44 | S29: =SUM($R$3:Table1[[#This Row],[Annual Consumption Value]]) / SUM(Table1[Annual Consumption Value]) -> 0.218294 | T29: =IF(Table1[[#This Row],[Cumulative %]]<=0.8, "A", IF(Table1[[#This Row],[Cumulative %]]<=0.95, "B", "C")) -> A
A30: AN-008 | B30: Azomac 500 | C30: Azithromycin | D30: Tablet | E30: Antibiotic | F30: =(Table1[[#This Row],[Unit Price]] * 0.9) * Table1[[#This Row],[Pcs per Box]] -> 486 | G30: 12 | H30: =Table1[[#This Row],[Cost Price]]/Table1[[#This Row],[Pcs per Box]] -> 40.5 | I30: 45 | J30: =SUMIF('Stock In'!C:C, Table1[[#This Row],[Medicine ID]], 'Stock In'!E:E) * Table1[[#This Row],[Pcs per Box]] -> 120 | K30: =SUMIF('Sales Log Table'!C:C, Table1[[#This Row],[Medicine ID]], 'Sales Log Table'!E:E) -> 0 | L30: =Table1[[#This Row],[Total Received]] - Table1[[#This Row],[Total Sold]] -> 120 | M30: 45 | N30: 46563 | O30: =IF(Table1[[#This Row],[Current Stock]] <= Table1[[#This Row],[Min Stock]], "REORDER NOW", "Good") -> Good | P30: =(Table1[[#This Row],[Unit Price]] - Table1[[#This Row],[Cost Per Pc]]) * Table1[[#This Row],[Total Sold]] -> 0 | R30: =(Table1[[#This Row],[Total Received]] / Table1[[#This Row],[Pcs per Box]]) * Table1[[#This Row],[Cost Price]] -> 4860 | S30: =SUM($R$3:Table1[[#This Row],[Annual Consumption Value]]) / SUM(Table1[Annual Consumption Value]) -> 0.23614007 | T30: =IF(Table1[[#This Row],[Cumulative %]]<=0.8, "A", IF(Table1[[#This Row],[Cumulative %]]<=0.95, "B", "C")) -> A
A31: AN-009 | B31: Roxim 200 | C31: Cefixime | D31: Capsule | E31: Antibiotic | F31: =(Table1[[#This Row],[Unit Price]] * 0.9) * Table1[[#This Row],[Pcs per Box]] -> 576 | G31: 16 | H31: =Table1[[#This Row],[Cost Price]]/Table1[[#This Row],[Pcs per Box]] -> 36 | I31: 40 | J31: =SUMIF('Stock In'!C:C, Table1[[#This Row],[Medicine ID]], 'Stock In'!E:E) * Table1[[#This Row],[Pcs per Box]] -> 48 | K31: =SUMIF('Sales Log Table'!C:C, Table1[[#This Row],[Medicine ID]], 'Sales Log Table'!E:E) -> 0 | L31: =Table1[[#This Row],[Total Received]] - Table1[[#This Row],[Total Sold]] -> 48 | M31: 16 | N31: 46563 | O31: =IF(Table1[[#This Row],[Current Stock]] <= Table1[[#This Row],[Min Stock]], "REORDER NOW", "Good") -> Good | P31: =(Table1[[#This Row],[Unit Price]] - Table1[[#This Row],[Cost Per Pc]]) * Table1[[#This Row],[Total Sold]] -> 0 | R31: =(Table1[[#This Row],[Total Received]] / Table1[[#This Row],[Pcs per Box]]) * Table1[[#This Row],[Cost Price]] -> 1728 | S31: =SUM($R$3:Table1[[#This Row],[Annual Consumption Value]]) / SUM(Table1[Annual Consumption Value]) -> 0.24248534 | T31: =IF(Table1[[#This Row],[Cumulative %]]<=0.8, "A", IF(Table1[[#This Row],[Cumulative %]]<=0.95, "B", "C")) -> A
A32: AN-010 | B32: Roxim 400 | C32: Cefixime | D32: Capsule | E32: Antibiotic | F32: =(Table1[[#This Row],[Unit Price]] * 0.9) * Table1[[#This Row],[Pcs per Box]] -> 495 | G32: 10 | H32: =Table1[[#This Row],[Cost Price]]/Table1[[#This Row],[Pcs per Box]] -> 49.5 | I32: 55 | J32: =SUMIF('Stock In'!C:C, Table1[[#This Row],[Medicine ID]], 'Stock In'!E:E) * Table1[[#This Row],[Pcs per Box]] -> 170 | K32: =SUMIF('Sales Log Table'!C:C, Table1[[#This Row],[Medicine ID]], 'Sales Log Table'!E:E) -> 0 | L32: =Table1[[#This Row],[Total Received]] - Table1[[#This Row],[Total Sold]] -> 170 | M32: 20 | N32: 46563 | O32: =IF(Table1[[#This Row],[Current Stock]] <= Table1[[#This Row],[Min Stock]], "REORDER NOW", "Good") -> Good | P32: =(Table1[[#This Row],[Unit Price]] - Table1[[#This Row],[Cost Per Pc]]) * Table1[[#This Row],[Total Sold]] -> 0 | R32: =(Table1[[#This Row],[Total Received]] / Table1[[#This Row],[Pcs per Box]]) * Table1[[#This Row],[Cost Price]] -> 8415 | S32: =SUM($R$3:Table1[[#This Row],[Annual Consumption Value]]) / SUM(Table1[Annual Consumption Value]) -> 0.27338549 | T32: =IF(Table1[[#This Row],[Cumulative %]]<=0.8, "A", IF(Table1[[#This Row],[Cumulative %]]<=0.95, "B", "C")) -> A
A33: AN-011 | B33: Cef-3 | C33: Cefixime | D33: Capsule | E33: Antibiotic | F33: =(Table1[[#This Row],[Unit Price]] * 0.9) * Table1[[#This Row],[Pcs per Box]] -> 567 | G33: 14 | H33: =Table1[[#This Row],[Cost Price]]/Table1[[#This Row],[Pcs per Box]] -> 40.5 | I33: 45 | J33: =SUMIF('Stock In'!C:C, Table1[[#This Row],[Medicine ID]], 'Stock In'!E:E) * Table1[[#This Row],[Pcs per Box]] -> 42 | K33: =SUMIF('Sales Log Table'!C:C, Table1[[#This Row],[Medicine ID]], 'Sales Log Table'!E:E) -> 0 | L33: =Table1[[#This Row],[Total Received]] - Table1[[#This Row],[Total Sold]] -> 42 | M33: 30 | N33: 46563 | O33: =IF(Table1[[#This Row],[Current Stock]] <= Table1[[#This Row],[Min Stock]], "REORDER NOW", "Good") -> Good | P33: =(Table1[[#This Row],[Unit Price]] - Table1[[#This Row],[Cost Per Pc]]) * Table1[[#This Row],[Total Sold]] -> 0 | R33: =(Table1[[#This Row],[Total Received]] / Table1[[#This Row],[Pcs per Box]]) * Table1[[#This Row],[Cost Price]] -> 1701 | S33: =SUM($R$3:Table1[[#This Row],[Annual Consumption Value]]) / SUM(Table1[Annual Consumption Value]) -> 0.27963161 | T33: =IF(Table1[[#This Row],[Cumulative %]]<=0.8, "A", IF(Table1[[#This Row],[Cumulative %]]<=0.95, "B", "C")) -> A
A34: AN-012 | B34: Cef-3 DS | C34: Cefixime | D34: Capsule | E34: Antibiotic | F34: =(Table1[[#This Row],[Unit Price]] * 0.9) * Table1[[#This Row],[Pcs per Box]] -> 756 | G34: 14 | H34: =Table1[[#This Row],[Cost Price]]/Table1[[#This Row],[Pcs per Box]] -> 54 | I34: 60 | J34: =SUMIF('Stock In'!C:C, Table1[[#This Row],[Medicine ID]], 'Stock In'!E:E) * Table1[[#This Row],[Pcs per Box]] -> 70 | K34: =SUMIF('Sales Log Table'!C:C, Table1[[#This Row],[Medicine ID]], 'Sales Log Table'!E:E) -> 0 | L34: =Table1[[#This Row],[Total Received]] - Table1[[#This Row],[Total Sold]] -> 70 | M34: 46 | N34: 46563 | O34: =IF(Table1[[#This Row],[Current Stock]] <= Table1[[#This Row],[Min Stock]], "REORDER NOW", "Good") -> Good | P34: =(Table1[[#This Row],[Unit Price]] - Table1[[#This Row],[Cost Per Pc]]) * Table1[[#This Row],[Total Sold]] -> 0 | R34: =(Table1[[#This Row],[Total Received]] / Table1[[#This Row],[Pcs per Box]]) * Table1[[#This Row],[Cost Price]] -> 3780 | S34: =SUM($R$3:Table1[[#This Row],[Annual Consumption Value]]) / SUM(Table1[Annual Consumption Value]) -> 0.29351189 | T34: =IF(Table1[[#This Row],[Cumulative %]]<=0.8, "A", IF(Table1[[#This Row],[Cumulative %]]<=0.95, "B", "C")) -> A
A35: AN-013 | B35: Crfim-3 | C35: Cefixime | D35: Capsule | E35: Antibiotic | F35: =(Table1[[#This Row],[Unit Price]] * 0.9) * Table1[[#This Row],[Pcs per Box]] -> 428.4 | G35: 14 | H35: =Table1[[#This Row],[Cost Price]]/Table1[[#This Row],[Pcs per Box]] -> 30.6 | I35: 34 | J35: =SUMIF('Stock In'!C:C, Table1[[#This Row],[Medicine ID]], 'Stock In'!E:E) * Table1[[#This Row],[Pcs per Box]] -> 84 | K35: =SUMIF('Sales Log Table'!C:C, Table1[[#This Row],[Medicine ID]], 'Sales Log Table'!E:E) -> 0 | L35: =Table1[[#This Row],[Total Received]] - Table1[[#This Row],[Total Sold]] -> 84 | M35: 76 | N35: 46563 | O35: =IF(Table1[[#This Row],[Current Stock]] <= Table1[[#This Row],[Min Stock]], "REORDER NOW", "Good") -> Good | P35: =(Table1[[#This Row],[Unit Price]] - Table1[[#This Row],[Cost Per Pc]]) * Table1[[#This Row],[Total Sold]] -> 0 | R35: =(Table1[[#This Row],[Total Received]] / Table1[[#This Row],[Pcs per Box]]) * Table1[[#This Row],[Cost Price]] -> 2570.4 | S35: =SUM($R$3:Table1[[#This Row],[Annual Consumption Value]]) / SUM(Table1[Annual Consumption Value]) -> 0.30295048 | T35: =IF(Table1[[#This Row],[Cumulative %]]<=0.8, "A", IF(Table1[[#This Row],[Cumulative %]]<=0.95, "B", "C")) -> A
A36: AN-014 | B36: Cefim-3 DS | C36: Cefixime | D36: Capsule | E36: Antibiotic | F36: =(Table1[[#This Row],[Unit Price]] * 0.9) * Table1[[#This Row],[Pcs per Box]] -> 756 | G36: 14 | H36: =Table1[[#This Row],[Cost Price]]/Table1[[#This Row],[Pcs per Box]] -> 54 | I36: 60 | J36: =SUMIF('Stock In'!C:C, Table1[[#This Row],[Medicine ID]], 'Stock In'!E:E) * Table1[[#This Row],[Pcs per Box]] -> 84 | K36: =SUMIF('Sales Log Table'!C:C, Table1[[#This Row],[Medicine ID]], 'Sales Log Table'!E:E) -> 0 | L36: =Table1[[#This Row],[Total Received]] - Table1[[#This Row],[Total Sold]] -> 84 | M36: 65 | N36: 46563 | O36: =IF(Table1[[#This Row],[Current Stock]] <= Table1[[#This Row],[Min Stock]], "REORDER NOW", "Good") -> Good | P36: =(Table1[[#This Row],[Unit Price]] - Table1[[#This Row],[Cost Per Pc]]) * Table1[[#This Row],[Total Sold]] -> 0 | R36: =(Table1[[#This Row],[Total Received]] / Table1[[#This Row],[Pcs per Box]]) * Table1[[#This Row],[Cost Price]] -> 4536 | S36: =SUM($R$3:Table1[[#This Row],[Annual Consumption Value]]) / SUM(Table1[Annual Consumption Value]) -> 0.31960682 | T36: =IF(Table1[[#This Row],[Cumulative %]]<=0.8, "A", IF(Table1[[#This Row],[Cumulative %]]<=0.95, "B", "C")) -> A
A37: AN-015 | B37: Denvar 200 | C37: Cefixime | D37: Capsule | E37: Antibiotic | F37: =(Table1[[#This Row],[Unit Price]] * 0.9) * Table1[[#This Row],[Pcs per Box]] -> 864 | G37: 24 | H37: =Table1[[#This Row],[Cost Price]]/Table1[[#This Row],[Pcs per Box]] -> 36 | I37: 40 | J37: =SUMIF('Stock In'!C:C, Table1[[#This Row],[Medicine ID]], 'Stock In'!E:E) * Table1[[#This Row],[Pcs per Box]] -> 72 | K37: =SUMIF('Sales Log Table'!C:C, Table1[[#This Row],[Medicine ID]], 'Sales Log Table'!E:E) -> 0 | L37: =Table1[[#This Row],[Total Received]] - Table1[[#This Row],[Total Sold]] -> 72 | M37: 47 | N37: 46563 | O37: =IF(Table1[[#This Row],[Current Stock]] <= Table1[[#This Row],[Min Stock]], "REORDER NOW", "Good") -> Good | P37: =(Table1[[#This Row],[Unit Price]] - Table1[[#This Row],[Cost Per Pc]]) * Table1[[#This Row],[Total Sold]] -> 0 | R37: =(Table1[[#This Row],[Total Received]] / Table1[[#This Row],[Pcs per Box]]) * Table1[[#This Row],[Cost Price]] -> 2592 | S37: =SUM($R$3:Table1[[#This Row],[Annual Consumption Value]]) / SUM(Table1[Annual Consumption Value]) -> 0.32912472 | T37: =IF(Table1[[#This Row],[Cumulative %]]<=0.8, "A", IF(Table1[[#This Row],[Cumulative %]]<=0.95, "B", "C")) -> A
A38: AN-016 | B38: Denvar 400 | C38: Cefixime | D38: Capsule | E38: Antibiotic | F38: =(Table1[[#This Row],[Unit Price]] * 0.9) * Table1[[#This Row],[Pcs per Box]] -> 972 | G38: 18 | H38: =Table1[[#This Row],[Cost Price]]/Table1[[#This Row],[Pcs per Box]] -> 54 | I38: 60 | J38: =SUMIF('Stock In'!C:C, Table1[[#This Row],[Medicine ID]], 'Stock In'!E:E) * Table1[[#This Row],[Pcs per Box]] -> 216 | K38: =SUMIF('Sales Log Table'!C:C, Table1[[#This Row],[Medicine ID]], 'Sales Log Table'!E:E) -> 0 | L38: =Table1[[#This Row],[Total Received]] - Table1[[#This Row],[Total Sold]] -> 216 | M38: 78 | N38: 46563 | O38: =IF(Table1[[#This Row],[Current Stock]] <= Table1[[#This Row],[Min Stock]], "REORDER NOW", "Good") -> Good | P38: =(Table1[[#This Row],[Unit Price]] - Table1[[#This Row],[Cost Per Pc]]) * Table1[[#This Row],[Total Sold]] -> 0 | R38: =(Table1[[#This Row],[Total Received]] / Table1[[#This Row],[Pcs per Box]]) * Table1[[#This Row],[Cost Price]] -> 11664 | S38: =SUM($R$3:Table1[[#This Row],[Annual Consumption Value]]) / SUM(Table1[Annual Consumption Value]) -> 0.37195529 | T38: =IF(Table1[[#This Row],[Cumulative %]]<=0.8, "A", IF(Table1[[#This Row],[Cumulative %]]<=0.95, "B", "C")) -> A
A39: AN-017 | B39: Fix-A | C39: Cefixime | D39: Capsule | E39: Antibiotic | F39: =(Table1[[#This Row],[Unit Price]] * 0.9) * Table1[[#This Row],[Pcs per Box]] -> 567 | G39: 14 | H39: =Table1[[#This Row],[Cost Price]]/Table1[[#This Row],[Pcs per Box]] -> 40.5 | I39: 45 | J39: =SUMIF('Stock In'!C:C, Table1[[#This Row],[Medicine ID]], 'Stock In'!E:E) * Table1[[#This Row],[Pcs per Box]] -> 42 | K39: =SUMIF('Sales Log Table'!C:C, Table1[[#This Row],[Medicine ID]], 'Sales Log Table'!E:E) -> 0 | L39: =Table1[[#This Row],[Total Received]] - Table1[[#This Row],[Total Sold]] -> 42 | M39: 29 | N39: 46563 | O39: =IF(Table1[[#This Row],[Current Stock]] <= Table1[[#This Row],[Min Stock]], "REORDER NOW", "Good") -> Good | P39: =(Table1[[#This Row],[Unit Price]] - Table1[[#This Row],[Cost Per Pc]]) * Table1[[#This Row],[Total Sold]] -> 0 | R39: =(Table1[[#This Row],[Total Received]] / Table1[[#This Row],[Pcs per Box]]) * Table1[[#This Row],[Cost Price]] -> 1701 | S39: =SUM($R$3:Table1[[#This Row],[Annual Consumption Value]]) / SUM(Table1[Annual Consumption Value]) -> 0.37820142 | T39: =IF(Table1[[#This Row],[Cumulative %]]<=0.8, "A", IF(Table1[[#This Row],[Cumulative %]]<=0.95, "B", "C")) -> A
A40: AN-018 | B40: Fix-A DS | C40: Cefixime | D40: Capsule | E40: Antibiotic | F40: =(Table1[[#This Row],[Unit Price]] * 0.9) * Table1[[#This Row],[Pcs per Box]] -> 756 | G40: 14 | H40: =Table1[[#This Row],[Cost Price]]/Table1[[#This Row],[Pcs per Box]] -> 54 | I40: 60 | J40: =SUMIF('Stock In'!C:C, Table1[[#This Row],[Medicine ID]], 'Stock In'!E:E) * Table1[[#This Row],[Pcs per Box]] -> 14 | K40: =SUMIF('Sales Log Table'!C:C, Table1[[#This Row],[Medicine ID]], 'Sales Log Table'!E:E) -> 0 | L40: =Table1[[#This Row],[Total Received]] - Table1[[#This Row],[Total Sold]] -> 14 | M40: 7 | N40: 46563 | O40: =IF(Table1[[#This Row],[Current Stock]] <= Table1[[#This Row],[Min Stock]], "REORDER NOW", "Good") -> Good | P40: =(Table1[[#This Row],[Unit Price]] - Table1[[#This Row],[Cost Per Pc]]) * Table1[[#This Row],[Total Sold]] -> 0 | R40: =(Table1[[#This Row],[Total Received]] / Table1[[#This Row],[Pcs per Box]]) * Table1[[#This Row],[Cost Price]] -> 756 | S40: =SUM($R$3:Table1[[#This Row],[Annual Consumption Value]]) / SUM(Table1[Annual Consumption Value]) -> 0.38097747 | T40: =IF(Table1[[#This Row],[Cumulative %]]<=0.8, "A", IF(Table1[[#This Row],[Cumulative %]]<=0.95, "B", "C")) -> A
A41: AN-019 | B41: Clavurox 250 | C41: Cefuroxime Axetil + Clavulanic Acid | D41: Tablet | E41: Antibiotic | F41: 431.23 | G41: 14 | H41: =Table1[[#This Row],[Cost Price]]/Table1[[#This Row],[Pcs per Box]] -> 30.802143 | I41: 35 | J41: =SUMIF('Stock In'!C:C, Table1[[#This Row],[Medicine ID]], 'Stock In'!E:E) * Table1[[#This Row],[Pcs per Box]] -> 28 | K41: =SUMIF('Sales Log Table'!C:C, Table1[[#This Row],[Medicine ID]], 'Sales Log Table'!E:E) -> 0 | L41: =Table1[[#This Row],[Total Received]] - Table1[[#This Row],[Total Sold]] -> 28 | M41: 14 | N41: 46563 | O41: =IF(Table1[[#This Row],[Current Stock]] <= Table1[[#This Row],[Min Stock]], "REORDER NOW", "Good") -> Good | P41: =(Table1[[#This Row],[Unit Price]] - Table1[[#This Row],[Cost Per Pc]]) * Table1[[#This Row],[Total Sold]] -> 0 | R41: =(Table1[[#This Row],[Total Received]] / Table1[[#This Row],[Pcs per Box]]) * Table1[[#This Row],[Cost Price]] -> 862.46 | S41: =SUM($R$3:Table1[[#This Row],[Annual Consumption Value]]) / SUM(Table1[Annual Consumption Value]) -> 0.38414446 | T41: =IF(Table1[[#This Row],[Cumulative %]]<=0.8, "A", IF(Table1[[#This Row],[Cumulative %]]<=0.95, "B", "C")) -> A
A42: AN-020 | B42: Zemicef PFS 50ml | C42: Cefixime | D42: Suspension | E42: Antibiotic | F42: 202.41 | G42: 1 | H42: =Table1[[#This Row],[Cost Price]]/Table1[[#This Row],[Pcs per Box]] -> 202.41 | I42: 230 | J42: =SUMIF('Stock In'!C:C, Table1[[#This Row],[Medicine ID]], 'Stock In'!E:E) * Table1[[#This Row],[Pcs per Box]] -> 30 | K42: =SUMIF('Sales Log Table'!C:C, Table1[[#This Row],[Medicine ID]], 'Sales Log Table'!E:E) -> 0 | L42: =Table1[[#This Row],[Total Received]] - Table1[[#This Row],[Total Sold]] -> 30 | M42: 1 | N42: 46563 | O42: =IF(Table1[[#This Row],[Current Stock]] <= Table1[[#This Row],[Min Stock]], "REORDER NOW", "Good") -> Good | P42: =(Table1[[#This Row],[Unit Price]] - Table1[[#This Row],[Cost Per Pc]]) * Table1[[#This Row],[Total Sold]] -> 0 | R42: =(Table1[[#This Row],[Total Received]] / Table1[[#This Row],[Pcs per Box]]) * Table1[[#This Row],[Cost Price]] -> 6072.3 | S42: =SUM($R$3:Table1[[#This Row],[Annual Consumption Value]]) / SUM(Table1[Annual Consumption Value]) -> 0.40644213 | T42: =IF(Table1[[#This Row],[Cumulative %]]<=0.8, "A", IF(Table1[[#This Row],[Cumulative %]]<=0.95, "B", "C")) -> A
A43: AN-021 | B43: Zemicef PFS 75ml | C43: Cefixime | D43: Suspension | E43: Antibiotic | F43: 211.21 | G43: 1 | H43: =Table1[[#This Row],[Cost Price]]/Table1[[#This Row],[Pcs per Box]] -> 211.21 | I43: 240 | J43: =SUMIF('Stock In'!C:C, Table1[[#This Row],[Medicine ID]], 'Stock In'!E:E) * Table1[[#This Row],[Pcs per Box]] -> 20 | K43: =SUMIF('Sales Log Table'!C:C, Table1[[#This Row],[Medicine ID]], 'Sales Log Table'!E:E) -> 0 | L43: =Table1[[#This Row],[Total Received]] - Table1[[#This Row],[Total Sold]] -> 20 | M43: 1 | N43: 46563 | O43: =IF(Table1[[#This Row],[Current Stock]] <= Table1[[#This Row],[Min Stock]], "REORDER NOW", "Good") -> Good | P43: =(Table1[[#This Row],[Unit Price]] - Table1[[#This Row],[Cost Per Pc]]) * Table1[[#This Row],[Total Sold]] -> 0 | R43: =(Table1[[#This Row],[Total Received]] / Table1[[#This Row],[Pcs per Box]]) * Table1[[#This Row],[Cost Price]] -> 4224.2 | S43: =SUM($R$3:Table1[[#This Row],[Annual Consumption Value]]) / SUM(Table1[Annual Consumption Value]) -> 0.42195353 | T43: =IF(Table1[[#This Row],[Cumulative %]]<=0.8, "A", IF(Table1[[#This Row],[Cumulative %]]<=0.95, "B", "C")) -> A
A44: AN-022 | B44: Roxim 50ml | C44: Cefixime | D44: Suspension | E44: Antibiotic | F44: 193.62 | G44: 1 | H44: =Table1[[#This Row],[Cost Price]]/Table1[[#This Row],[Pcs per Box]] -> 193.62 | I44: 220 | J44: =SUMIF('Stock In'!C:C, Table1[[#This Row],[Medicine ID]], 'Stock In'!E:E) * Table1[[#This Row],[Pcs per Box]] -> 22 | K44: =SUMIF('Sales Log Table'!C:C, Table1[[#This Row],[Medicine ID]], 'Sales Log Table'!E:E) -> 0 | L44: =Table1[[#This Row],[Total Received]] - Table1[[#This Row],[Total Sold]] -> 22 | M44: 1 | N44: 46563 | O44: =IF(Table1[[#This Row],[Current Stock]] <= Table1[[#This Row],[Min Stock]], "REORDER NOW", "Good") -> Good | P44: =(Table1[[#This Row],[Unit Price]] - Table1[[#This Row],[Cost Per Pc]]) * Table1[[#This Row],[Total Sold]] -> 0 | R44: =(Table1[[#This Row],[Total Received]] / Table1[[#This Row],[Pcs per Box]]) * Table1[[#This Row],[Cost Price]] -> 4259.64 | S44: =SUM($R$3:Table1[[#This Row],[Annual Consumption Value]]) / SUM(Table1[Annual Consumption Value]) -> 0.43759506 | T44: =IF(Table1[[#This Row],[Cumulative %]]<=0.8, "A", IF(Table1[[#This Row],[Cumulative %]]<=0.95, "B", "C")) -> A
A45: AN-023 | B45: Azin 30ml | C45: Azithromycin | D45: Suspension | E45: Antibiotic | F45: 162.81 | G45: 1 | H45: =Table1[[#This Row],[Cost Price]]/Table1[[#This Row],[Pcs per Box]] -> 162.81 | I45: 185 | J45: =SUMIF('Stock In'!C:C, Table1[[#This Row],[Medicine ID]], 'Stock In'!E:E) * Table1[[#This Row],[Pcs per Box]] -> 2 | K45: =SUMIF('Sales Log Table'!C:C, Table1[[#This Row],[Medicine ID]], 'Sales Log Table'!E:E) -> 0 | L45: =Table1[[#This Row],[Total Received]] - Table1[[#This Row],[Total Sold]] -> 2 | M45: 1 | N45: 46563 | O45: =IF(Table1[[#This Row],[Current Stock]] <= Table1[[#This Row],[Min Stock]], "REORDER NOW", "Good") -> Good | P45: =(Table1[[#This Row],[Unit Price]] - Table1[[#This Row],[Cost Per Pc]]) * Table1[[#This Row],[Total Sold]] -> 0 | R45: =(Table1[[#This Row],[Total Received]] / Table1[[#This Row],[Pcs per Box]]) * Table1[[#This Row],[Cost Price]] -> 325.62 | S45: =SUM($R$3:Table1[[#This Row],[Annual Consumption Value]]) / SUM(Table1[Annual Consumption Value]) -> 0.43879074 | T45: =IF(Table1[[#This Row],[Cumulative %]]<=0.8, "A", IF(Table1[[#This Row],[Cumulative %]]<=0.95, "B", "C")) -> A
A46: AN-024 | B46: Murein 500mg | C46: Flucloxacillin Sodium | D46: Capsule | E46: Antibiotic | F46: 258.74 | G46: 28 | H46: =Table1[[#This Row],[Cost Price]]/Table1[[#This Row],[Pcs per Box]] -> 9.2407143 | I46: 10.5 | J46: =SUMIF('Stock In'!C:C, Table1[[#This Row],[Medicine ID]], 'Stock In'!E:E) * Table1[[#This Row],[Pcs per Box]] -> 448 | K46: =SUMIF('Sales Log Table'!C:C, Table1[[#This Row],[Medicine ID]], 'Sales Log Table'!E:E) -> 0 | L46: =Table1[[#This Row],[Total Received]] - Table1[[#This Row],[Total Sold]] -> 448 | O46: =IF(Table1[[#This Row],[Current Stock]] <= Table1[[#This Row],[Min Stock]], "REORDER NOW", "Good") -> Good | P46: =(Table1[[#This Row],[Unit Price]] - Table1[[#This Row],[Cost Per Pc]]) * Table1[[#This Row],[Total Sold]] -> 0 | R46: =(Table1[[#This Row],[Total Received]] / Table1[[#This Row],[Pcs per Box]]) * Table1[[#This Row],[Cost Price]] -> 4139.84 | S46: =SUM($R$3:Table1[[#This Row],[Annual Consumption Value]]) / SUM(Table1[Annual Consumption Value]) -> 0.45399237 | T46: =IF(Table1[[#This Row],[Cumulative %]]<=0.8, "A", IF(Table1[[#This Row],[Cumulative %]]<=0.95, "B", "C")) -> A
A47: AN-025 | B47: Ocimax 500mg | C47: Ciprofloxacin | D47: Tablet | E47: Antibiotic | F47: =(Table1[[#This Row],[Unit Price]] * 0.9) * Table1[[#This Row],[Pcs per Box]] -> 405 | G47: 30 | H47: =Table1[[#This Row],[Cost Price]]/Table1[[#This Row],[Pcs per Box]] -> 13.5 | I47: 15 | J47: =SUMIF('Stock In'!C:C, Table1[[#This Row],[Medicine ID]], 'Stock In'!E:E) * Table1[[#This Row],[Pcs per Box]] -> 360 | K47: =SUMIF('Sales Log Table'!C:C, Table1[[#This Row],[Medicine ID]], 'Sales Log Table'!E:E) -> 0 | L47: =Table1[[#This Row],[Total Received]] - Table1[[#This Row],[Total Sold]] -> 360 | O47: =IF(Table1[[#This Row],[Current Stock]] <= Table1[[#This Row],[Min Stock]], "REORDER NOW", "Good") -> Good | P47: =(Table1[[#This Row],[Unit Price]] - Table1[[#This Row],[Cost Per Pc]]) * Table1[[#This Row],[Total Sold]] -> 0 | R47: =(Table1[[#This Row],[Total Received]] / Table1[[#This Row],[Pcs per Box]]) * Table1[[#This Row],[Cost Price]] -> 4860 | S47: =SUM($R$3:Table1[[#This Row],[Annual Consumption Value]]) / SUM(Table1[Annual Consumption Value]) -> 0.47183844 | T47: =IF(Table1[[#This Row],[Cumulative %]]<=0.8, "A", IF(Table1[[#This Row],[Cumulative %]]<=0.95, "B", "C")) -> A
A48: AN-026 | B48: Ciprocin 500mg | C48: Ciprofloxacin | D48: Tablet | E48: Antibiotic | F48: =(Table1[[#This Row],[Unit Price]] * 0.9) * Table1[[#This Row],[Pcs per Box]] -> 0 | G48: 30 | H48: =Table1[[#This Row],[Cost Price]]/Table1[[#This Row],[Pcs per Box]] -> 0 | J48: =SUMIF('Stock In'!C:C, Table1[[#This Row],[Medicine ID]], 'Stock In'!E:E) * Table1[[#This Row],[Pcs per Box]] -> 30 | K48: =SUMIF('Sales Log Table'!C:C, Table1[[#This Row],[Medicine ID]], 'Sales Log Table'!E:E) -> 0 | L48: =Table1[[#This Row],[Total Received]] - Table1[[#This Row],[Total Sold]] -> 30 | N48: 46565 | O48: =IF(Table1[[#This Row],[Current Stock]] <= Table1[[#This Row],[Min Stock]], "REORDER NOW", "Good") -> Good | P48: =(Table1[[#This Row],[Unit Price]] - Table1[[#This Row],[Cost Per Pc]]) * Table1[[#This Row],[Total Sold]] -> 0 | R48: =(Table1[[#This Row],[Total Received]] / Table1[[#This Row],[Pcs per Box]]) * Table1[[#This Row],[Cost Price]] -> 0 | S48: =SUM($R$3:Table1[[#This Row],[Annual Consumption Value]]) / SUM(Table1[Annual Consumption Value]) -> 0.47183844 | T48: =IF(Table1[[#This Row],[Cumulative %]]<=0.8, "A", IF(Table1[[#This Row],[Cumulative %]]<=0.95, "B", "C")) -> A
A49: AN-027 | B49: Ciprocin 250mg | C49: Ciprofloxacin | D49: Tablet | E49: Antibiotic | F49: =(Table1[[#This Row],[Unit Price]] * 0.9) * Table1[[#This Row],[Pcs per Box]] -> 0 | G49: 50 | H49: =Table1[[#This Row],[Cost Price]]/Table1[[#This Row],[Pcs per Box]] -> 0 | J49: =SUMIF('Stock In'!C:C, Table1[[#This Row],[Medicine ID]], 'Stock In'!E:E) * Table1[[#This Row],[Pcs per Box]] -> 50 | K49: =SUMIF('Sales Log Table'!C:C, Table1[[#This Row],[Medicine ID]], 'Sales Log Table'!E:E) -> 0 | L49: =Table1[[#This Row],[Total Received]] - Table1[[#This Row],[Total Sold]] -> 50 | N49: 46566 | O49: =IF(Table1[[#This Row],[Current Stock]] <= Table1[[#This Row],[Min Stock]], "REORDER NOW", "Good") -> Good | P49: =(Table1[[#This Row],[Unit Price]] - Table1[[#This Row],[Cost Per Pc]]) * Table1[[#This Row],[Total Sold]] -> 0 | R49: =(Table1[[#This Row],[Total Received]] / Table1[[#This Row],[Pcs per Box]]) * Table1[[#This Row],[Cost Price]] -> 0 | S49: =SUM($R$3:Table1[[#This Row],[Annual Consumption Value]]) / SUM(Table1[Annual Consumption Value]) -> 0.47183844 | T49: =IF(Table1[[#This Row],[Cumulative %]]<=0.8, "A", IF(Table1[[#This Row],[Cumulative %]]<=0.95, "B", "C")) -> A
A50: AN-028 | B50: Furoclav 500mg | C50: Cefuroxime Axetil + Clavulanic Acid | D50: Tablet | E50: Antibiotic | F50: 739.28 | G50: 14 | H50: =Table1[[#This Row],[Cost Price]]/Table1[[#This Row],[Pcs per Box]] -> 52.805714 | J50: =SUMIF('Stock In'!C:C, Table1[[#This Row],[Medicine ID]], 'Stock In'!E:E) * Table1[[#This Row],[Pcs per Box]] -> 28 | K50: =SUMIF('Sales Log Table'!C:C, Table1[[#This Row],[Medicine ID]], 'Sales Log Table'!E:E) -> 0 | L50: =Table1[[#This Row],[Total Received]] - Table1[[#This Row],[Total Sold]] -> 28 | O50: =IF(Table1[[#This Row],[Current Stock]] <= Table1[[#This Row],[Min Stock]], "REORDER NOW", "Good") -> Good | P50: =(Table1[[#This Row],[Unit Price]] - Table1[[#This Row],[Cost Per Pc]]) * Table1[[#This Row],[Total Sold]] -> 0 | R50: =(Table1[[#This Row],[Total Received]] / Table1[[#This Row],[Pcs per Box]]) * Table1[[#This Row],[Cost Price]] -> 1478.56 | S50: =SUM($R$3:Table1[[#This Row],[Annual Consumption Value]]) / SUM(Table1[Annual Consumption Value]) -> 0.47726776 | T50: =IF(Table1[[#This Row],[Cumulative %]]<=0.8, "A", IF(Table1[[#This Row],[Cumulative %]]<=0.95, "B", "C")) -> A
A51: AN-029 | B51: Zithrin 500mg | C51: Azithromycin | D51: Tablet | E51: Antibiotic | F51: 528.15 | G51: 15 | H51: =Table1[[#This Row],[Cost Price]]/Table1[[#This Row],[Pcs per Box]] -> 35.21 | J51: =SUMIF('Stock In'!C:C, Table1[[#This Row],[Medicine ID]], 'Stock In'!E:E) * Table1[[#This Row],[Pcs per Box]] -> 150 | K51: =SUMIF('Sales Log Table'!C:C, Table1[[#This Row],[Medicine ID]], 'Sales Log Table'!E:E) -> 0 | L51: =Table1[[#This Row],[Total Received]] - Table1[[#This Row],[Total Sold]] -> 150 | O51: =IF(Table1[[#This Row],[Current Stock]] <= Table1[[#This Row],[Min Stock]], "REORDER NOW", "Good") -> Good | P51: =(Table1[[#This Row],[Unit Price]] - Table1[[#This Row],[Cost Per Pc]]) * Table1[[#This Row],[Total Sold]] -> 0 | R51: =(Table1[[#This Row],[Total Received]] / Table1[[#This Row],[Pcs per Box]]) * Table1[[#This Row],[Cost Price]] -> 5281.5 | S51: =SUM($R$3:Table1[[#This Row],[Annual Consumption Value]]) / SUM(Table1[Annual Consumption Value]) -> 0.49666159 | T51: =IF(Table1[[#This Row],[Cumulative %]]<=0.8, "A", IF(Table1[[#This Row],[Cumulative %]]<=0.95, "B", "C")) -> A
A52: AN-030 | B52: Ocimax 60ml PFS | C52: Ciprofloxacin | D52: Suspension | E52: Antibiotic | F52: 88 | G52: 1 | H52: =Table1[[#This Row],[Cost Price]]/Table1[[#This Row],[Pcs per Box]] -> 88 | I52: 100 | J52: =SUMIF('Stock In'!C:C, Table1[[#This Row],[Medicine ID]], 'Stock In'!E:E) * Table1[[#This Row],[Pcs per Box]] -> 0 | K52: =SUMIF('Sales Log Table'!C:C, Table1[[#This Row],[Medicine ID]], 'Sales Log Table'!E:E) -> 0 | L52: =Table1[[#This Row],[Total Received]] - Table1[[#This Row],[Total Sold]] -> 0 | N52: 46582 | O52: =IF(Table1[[#This Row],[Current Stock]] <= Table1[[#This Row],[Min Stock]], "REORDER NOW", "Good") -> REORDER NOW | P52: =(Table1[[#This Row],[Unit Price]] - Table1[[#This Row],[Cost Per Pc]]) * Table1[[#This Row],[Total Sold]] -> 0 | R52: =(Table1[[#This Row],[Total Received]] / Table1[[#This Row],[Pcs per Box]]) * Table1[[#This Row],[Cost Price]] -> 0 | S52: =SUM($R$3:Table1[[#This Row],[Annual Consumption Value]]) / SUM(Table1[Annual Consumption Value]) -> 0.49666159 | T52: =IF(Table1[[#This Row],[Cumulative %]]<=0.8, "A", IF(Table1[[#This Row],[Cumulative %]]<=0.95, "B", "C")) -> A
A53: ANT-001 | B53: Delentin | C53: Pyrantel Pamoate | D53: Suspension | E53: Ascaris / Necator | F53: 14.12 | G53: 1 | H53: 14.12 | I53: 16.05 | J53: =SUMIF('Stock In'!C:C, Table1[[#This Row],[Medicine ID]], 'Stock In'!E:E) * Table1[[#This Row],[Pcs per Box]] -> 10 | K53: =SUMIF('Sales Log Table'!C:C, Table1[[#This Row],[Medicine ID]], 'Sales Log Table'!E:E) -> 0 | L53: =Table1[[#This Row],[Total Received]] - Table1[[#This Row],[Total Sold]] -> 10 | N53: 46564 | O53: =IF(Table1[[#This Row],[Current Stock]] <= Table1[[#This Row],[Min Stock]], "REORDER NOW", "Good") -> Good | P53: =(Table1[[#This Row],[Unit Price]] - Table1[[#This Row],[Cost Per Pc]]) * Table1[[#This Row],[Total Sold]] -> 0 | R53: =(Table1[[#This Row],[Total Received]] / Table1[[#This Row],[Pcs per Box]]) * Table1[[#This Row],[Cost Price]] -> 141.2 | S53: =SUM($R$3:Table1[[#This Row],[Annual Consumption Value]]) / SUM(Table1[Annual Consumption Value]) -> 0.49718008 | T53: =IF(Table1[[#This Row],[Cumulative %]]<=0.8, "A", IF(Table1[[#This Row],[Cumulative %]]<=0.95, "B", "C")) -> A
A54: ANT-002 | B54: Alben | C54: Albendazole | D54: Suspension | E54: Ascaris / Necator | F54: =(Table1[[#This Row],[Unit Price]] * 0.9) * Table1[[#This Row],[Pcs per Box]] -> 0 | G54: 1 | H54: =Table1[[#This Row],[Cost Price]]/Table1[[#This Row],[Pcs per Box]] -> 0 | J54: =SUMIF('Stock In'!C:C, Table1[[#This Row],[Medicine ID]], 'Stock In'!E:E) * Table1[[#This Row],[Pcs per Box]] -> 0 | K54: =SUMIF('Sales Log Table'!C:C, Table1[[#This Row],[Medicine ID]], 'Sales Log Table'!E:E) -> 0 | L54: =Table1[[#This Row],[Total Received]] - Table1[[#This Row],[Total Sold]] -> 0 | N54: 46567 | O54: =IF(Table1[[#This Row],[Current Stock]] <= Table1[[#This Row],[Min Stock]], "REORDER NOW", "Good") -> REORDER NOW | P54: =(Table1[[#This Row],[Unit Price]] - Table1[[#This Row],[Cost Per Pc]]) * Table1[[#This Row],[Total Sold]] -> 0 | R54: =(Table1[[#This Row],[Total Received]] / Table1[[#This Row],[Pcs per Box]]) * Table1[[#This Row],[Cost Price]] -> 0 | S54: =SUM($R$3:Table1[[#This Row],[Annual Consumption Value]]) / SUM(Table1[Annual Consumption Value]) -> 0.49718008 | T54: =IF(Table1[[#This Row],[Cumulative %]]<=0.8, "A", IF(Table1[[#This Row],[Cumulative %]]<=0.95, "B", "C")) -> A
A55: ANT-003 | B55: Alben DS | C55: Albendazole | D55: Tablet | E55: Ascaris / Necator | F55: =(Table1[[#This Row],[Unit Price]] * 0.9) * Table1[[#This Row],[Pcs per Box]] -> 450 | G55: 100 | H55: =Table1[[#This Row],[Cost Price]]/Table1[[#This Row],[Pcs per Box]] -> 4.5 | I55: 5 | J55: =SUMIF('Stock In'!C:C, Table1[[#This Row],[Medicine ID]], 'Stock In'!E:E) * Table1[[#This Row],[Pcs per Box]] -> 0 | K55: =SUMIF('Sales Log Table'!C:C, Table1[[#This Row],[Medicine ID]], 'Sales Log Table'!E:E) -> 0 | L55: =Table1[[#This Row],[Total Received]] - Table1[[#This Row],[Total Sold]] -> 0 | N55: 46568 | O55: =IF(Table1[[#This Row],[Current Stock]] <= Table1[[#This Row],[Min Stock]], "REORDER NOW", "Good") -> REORDER NOW | P55: =(Table1[[#This Row],[Unit Price]] - Table1[[#This Row],[Cost Per Pc]]) * Table1[[#This Row],[Total Sold]] -> 0 | R55: =(Table1[[#This Row],[Total Received]] / Table1[[#This Row],[Pcs per Box]]) * Table1[[#This Row],[Cost Price]] -> 0 | S55: =SUM($R$3:Table1[[#This Row],[Annual Consumption Value]]) / SUM(Table1[Annual Consumption Value]) -> 0.49718008 | T55: =IF(Table1[[#This Row],[Cumulative %]]<=0.8, "A", IF(Table1[[#This Row],[Cumulative %]]<=0.95, "B", "C")) -> A
A56: CAL-001 | B56: Aquacal-D | C56: Algae Calcium + D3 | D56: Tablet | E56: Calcium and Vitamin D3 Deficiency | F56: 580.84 | G56: 60 | H56: =Table1[[#This Row],[Cost Price]]/Table1[[#This Row],[Pcs per Box]] -> 9.6806667 | I56: 11 | J56: =SUMIF('Stock In'!C:C, Table1[[#This Row],[Medicine ID]], 'Stock In'!E:E) * Table1[[#This Row],[Pcs per Box]] -> 300 | K56: =SUMIF('Sales Log Table'!C:C, Table1[[#This Row],[Medicine ID]], 'Sales Log Table'!E:E) -> 0 | L56: =Table1[[#This Row],[Total Received]] - Table1[[#This Row],[Total Sold]] -> 300 | M56: 100 | N56: 46563 | O56: =IF(Table1[[#This Row],[Current Stock]] <= Table1[[#This Row],[Min Stock]], "REORDER NOW", "Good") -> Good | P56: =(Table1[[#This Row],[Unit Price]] - Table1[[#This Row],[Cost Per Pc]]) * Table1[[#This Row],[Total Sold]] -> 0 | R56: =(Table1[[#This Row],[Total Received]] / Table1[[#This Row],[Pcs per Box]]) * Table1[[#This Row],[Cost Price]] -> 2904.2 | S56: =SUM($R$3:Table1[[#This Row],[Annual Consumption Value]]) / SUM(Table1[Annual Consumption Value]) -> 0.5078444 | T56: =IF(Table1[[#This Row],[Cumulative %]]<=0.8, "A", IF(Table1[[#This Row],[Cumulative %]]<=0.95, "B", "C")) -> A
A57: CAL-002 | B57: Kalcoral-C | C57: Calcium + Vitamin C | D57: Effervescent Tablet | E57: Calcium and Vitamin C Deficiency | F57: 184.81 | G57: 1 | H57: =Table1[[#This Row],[Cost Price]]/Table1[[#This Row],[Pcs per Box]] -> 184.81 | I57: 210 | J57: =SUMIF('Stock In'!C:C, Table1[[#This Row],[Medicine ID]], 'Stock In'!E:E) * Table1[[#This Row],[Pcs per Box]] -> 10 | K57: =SUMIF('Sales Log Table'!C:C, Table1[[#This Row],[Medicine ID]], 'Sales Log Table'!E:E) -> 0 | L57: =Table1[[#This Row],[Total Received]] - Table1[[#This Row],[Total Sold]] -> 10 | M57: 1 | N57: 46563 | O57: =IF(Table1[[#This Row],[Current Stock]] <= Table1[[#This Row],[Min Stock]], "REORDER NOW", "Good") -> Good | P57: =(Table1[[#This Row],[Unit Price]] - Table1[[#This Row],[Cost Per Pc]]) * Table1[[#This Row],[Total Sold]] -> 0 | R57: =(Table1[[#This Row],[Total Received]] / Table1[[#This Row],[Pcs per Box]]) * Table1[[#This Row],[Cost Price]] -> 1848.1 | S57: =SUM($R$3:Table1[[#This Row],[Annual Consumption Value]]) / SUM(Table1[Annual Consumption Value]) -> 0.51463068 | T57: =IF(Table1[[#This Row],[Cumulative %]]<=0.8, "A", IF(Table1[[#This Row],[Cumulative %]]<=0.95, "B", "C")) -> A
A58: CAL-003 | B58: Kalcoral-D | C58: Coral Calcium + Vitamin D3 | D58: Tablet | E58: Bone Health / Calcium Deficiency | F58: 580.24 | G58: 60 | H58: =Table1[[#This Row],[Cost Price]]/Table1[[#This Row],[Pcs per Box]] -> 9.6706667 | I58: 11 | J58: =SUMIF('Stock In'!C:C, Table1[[#This Row],[Medicine ID]], 'Stock In'!E:E) * Table1[[#This Row],[Pcs per Box]] -> 300 | K58: =SUMIF('Sales Log Table'!C:C, Table1[[#This Row],[Medicine ID]], 'Sales Log Table'!E:E) -> 0 | L58: =Table1[[#This Row],[Total Received]] - Table1[[#This Row],[Total Sold]] -> 300 | M58: 60 | N58: 46563 | O58: =IF(Table1[[#This Row],[Current Stock]] <= Table1[[#This Row],[Min Stock]], "REORDER NOW", "Good") -> Good | P58: =(Table1[[#This Row],[Unit Price]] - Table1[[#This Row],[Cost Per Pc]]) * Table1[[#This Row],[Total Sold]] -> 0 | R58: =(Table1[[#This Row],[Total Received]] / Table1[[#This Row],[Pcs per Box]]) * Table1[[#This Row],[Cost Price]] -> 2901.2 | S58: =SUM($R$3:Table1[[#This Row],[Annual Consumption Value]]) / SUM(Table1[Annual Consumption Value]) -> 0.52528397 | T58: =IF(Table1[[#This Row],[Cumulative %]]<=0.8, "A", IF(Table1[[#This Row],[Cumulative %]]<=0.95, "B", "C")) -> A
A59: CAL-004 | B59: Kalcoral-DX | C59: Coral Calcium + Vitamin D3 | D59: Tablet | E59: Bone Health / Calcium Deficiency | F59: 563.24 | G59: 40 | H59: =Table1[[#This Row],[Cost Price]]/Table1[[#This Row],[Pcs per Box]] -> 14.081 | I59: 16 | J59: =SUMIF('Stock In'!C:C, Table1[[#This Row],[Medicine ID]], 'Stock In'!E:E) * Table1[[#This Row],[Pcs per Box]] -> 120 | K59: =SUMIF('Sales Log Table'!C:C, Table1[[#This Row],[Medicine ID]], 'Sales Log Table'!E:E) -> 0 | L59: =Table1[[#This Row],[Total Received]] - Table1[[#This Row],[Total Sold]] -> 120 | M59: 40 | N59: 46563 | O59: =IF(Table1[[#This Row],[Current Stock]] <= Table1[[#This Row],[Min Stock]], "REORDER NOW", "Good") -> Good | P59: =(Table1[[#This Row],[Unit Price]] - Table1[[#This Row],[Cost Per Pc]]) * Table1[[#This Row],[Total Sold]] -> 0 | R59: =(Table1[[#This Row],[Total Received]] / Table1[[#This Row],[Pcs per Box]]) * Table1[[#This Row],[Cost Price]] -> 1689.72 | S59: =SUM($R$3:Table1[[#This Row],[Annual Consumption Value]]) / SUM(Table1[Annual Consumption Value]) -> 0.53148868 | T59: =IF(Table1[[#This Row],[Cumulative %]]<=0.8, "A", IF(Table1[[#This Row],[Cumulative %]]<=0.95, "B", "C")) -> A
A60: CAL-005 | B60: CoracaD-C | C60: Calcium + Vitamin C | D60: Effervescent Tablet | E60: Calcium and Vitamin C Deficiency | F60: 176.02 | G60: 1 | H60: =Table1[[#This Row],[Cost Price]]/Table1[[#This Row],[Pcs per Box]] -> 176.02 | I60: 200 | J60: =SUMIF('Stock In'!C:C, Table1[[#This Row],[Medicine ID]], 'Stock In'!E:E) * Table1[[#This Row],[Pcs per Box]] -> 8 | K60: =SUMIF('Sales Log Table'!C:C, Table1[[#This Row],[Medicine ID]], 'Sales Log Table'!E:E) -> 0 | L60: =Table1[[#This Row],[Total Received]] - Table1[[#This Row],[Total Sold]] -> 8 | M60: 1 | N60: 46563 | O60: =IF(Table1[[#This Row],[Current Stock]] <= Table1[[#This Row],[Min Stock]], "REORDER NOW", "Good") -> Good | P60: =(Table1[[#This Row],[Unit Price]] - Table1[[#This Row],[Cost Per Pc]]) * Table1[[#This Row],[Total Sold]] -> 0 | R60: =(Table1[[#This Row],[Total Received]] / Table1[[#This Row],[Pcs per Box]]) * Table1[[#This Row],[Cost Price]] -> 1408.16 | S60: =SUM($R$3:Table1[[#This Row],[Annual Consumption Value]]) / SUM(Table1[Annual Consumption Value]) -> 0.53665949 | T60: =IF(Table1[[#This Row],[Cumulative %]]<=0.8, "A", IF(Table1[[#This Row],[Cumulative %]]<=0.95, "B", "C")) -> A
A61: CAL-006 | B61: Ostocal-D | C61: Calcium + Vitamin D3 | D61: Tablet | E61: Bone Health / Calcium Deficiency | F61: 211.21 | G61: 30 | H61: =Table1[[#This Row],[Cost Price]]/Table1[[#This Row],[Pcs per Box]] -> 7.0403333 | I61: 240 | J61: =SUMIF('Stock In'!C:C, Table1[[#This Row],[Medicine ID]], 'Stock In'!E:E) * Table1[[#This Row],[Pcs per Box]] -> 330 | K61: =SUMIF('Sales Log Table'!C:C, Table1[[#This Row],[Medicine ID]], 'Sales Log Table'!E:E) -> 0 | L61: =Table1[[#This Row],[Total Received]] - Table1[[#This Row],[Total Sold]] -> 330 | M61: 30 | N61: 46563 | O61: =IF(Table1[[#This Row],[Current Stock]] <= Table1[[#This Row],[Min Stock]], "REORDER NOW", "Good") -> Good | P61: =(Table1[[#This Row],[Unit Price]] - Table1[[#This Row],[Cost Per Pc]]) * Table1[[#This Row],[Total Sold]] -> 0 | R61: =(Table1[[#This Row],[Total Received]] / Table1[[#This Row],[Pcs per Box]]) * Table1[[#This Row],[Cost Price]] -> 2323.31 | S61: =SUM($R$3:Table1[[#This Row],[Annual Consumption Value]]) / SUM(Table1[Annual Consumption Value]) -> 0.54519075 | T61: =IF(Table1[[#This Row],[Cumulative %]]<=0.8, "A", IF(Table1[[#This Row],[Cumulative %]]<=0.95, "B", "C")) -> A
A62: CAL-007 | B62: Coralcin-D | C62: Coral Calcium + Vitamin D3 | D62: Tablet | E62: Bone Health / Calcium Deficiency | F62: 607.2 | G62: 60 | H62: =Table1[[#This Row],[Cost Price]]/Table1[[#This Row],[Pcs per Box]] -> 10.12 | I62: 11 | J62: =SUMIF('Stock In'!C:C, Table1[[#This Row],[Medicine ID]], 'Stock In'!E:E) * Table1[[#This Row],[Pcs per Box]] -> 60 | K62: =SUMIF('Sales Log Table'!C:C, Table1[[#This Row],[Medicine ID]], 'Sales Log Table'!E:E) -> 50 | L62: =Table1[[#This Row],[Total Received]] - Table1[[#This Row],[Total Sold]] -> 10 | M62: 10 | N62: 46563 | O62: =IF(Table1[[#This Row],[Current Stock]] <= Table1[[#This Row],[Min Stock]], "REORDER NOW", "Good") -> REORDER NOW | P62: =(Table1[[#This Row],[Unit Price]] - Table1[[#This Row],[Cost Per Pc]]) * Table1[[#This Row],[Total Sold]] -> 44 | R62: =(Table1[[#This Row],[Total Received]] / Table1[[#This Row],[Pcs per Box]]) * Table1[[#This Row],[Cost Price]] -> 607.2 | S62: =SUM($R$3:Table1[[#This Row],[Annual Consumption Value]]) / SUM(Table1[Annual Consumption Value]) -> 0.54742041 | T62: =IF(Table1[[#This Row],[Cumulative %]]<=0.8, "A", IF(Table1[[#This Row],[Cumulative %]]<=0.95, "B", "C")) -> A
A63: CARD-001 | B63: Betabis 5mg | C63: Bisoprolol Fumarate | D63: Tablet | E63: Hypertension / Heart Failure | F63: 303.6 | G63: 30 | H63: =Table1[[#This Row],[Cost Price]]/Table1[[#This Row],[Pcs per Box]] -> 10.12 | I63: 11.5 | J63: =SUMIF('Stock In'!C:C, Table1[[#This Row],[Medicine ID]], 'Stock In'!E:E) * Table1[[#This Row],[Pcs per Box]] -> 60 | K63: =SUMIF('Sales Log Table'!C:C, Table1[[#This Row],[Medicine ID]], 'Sales Log Table'!E:E) -> 0 | L63: =Table1[[#This Row],[Total Received]] - Table1[[#This Row],[Total Sold]] -> 60 | M63: 30 | N63: 46563 | O63: =IF(Table1[[#This Row],[Current Stock]] <= Table1[[#This Row],[Min Stock]], "REORDER NOW", "Good") -> Good | P63: =(Table1[[#This Row],[Unit Price]] - Table1[[#This Row],[Cost Per Pc]]) * Table1[[#This Row],[Total Sold]] -> 0 | R63: =(Table1[[#This Row],[Total Received]] / Table1[[#This Row],[Pcs per Box]]) * Table1[[#This Row],[Cost Price]] -> 607.2 | S63: =SUM($R$3:Table1[[#This Row],[Annual Consumption Value]]) / SUM(Table1[Annual Consumption Value]) -> 0.54965007 | T63: =IF(Table1[[#This Row],[Cumulative %]]<=0.8, "A", IF(Table1[[#This Row],[Cumulative %]]<=0.95, "B", "C")) -> A
A64: EAR-001 | B64: OTO-4 | C64: Ofloxacin + Clotrimazole + Beclomethasone + Lidocaine | D64: Drop | E64: Ear Infection / Inflammation | F64: 132 | G64: 1 | H64: =Table1[[#This Row],[Cost Price]]/Table1[[#This Row],[Pcs per Box]] -> 132 | I64: 150 | J64: =SUMIF('Stock In'!C:C, Table1[[#This Row],[Medicine ID]], 'Stock In'!E:E) * Table1[[#This Row],[Pcs per Box]] -> 5 | K64: =SUMIF('Sales Log Table'!C:C, Table1[[#This Row],[Medicine ID]], 'Sales Log Table'!E:E) -> 0 | L64: =Table1[[#This Row],[Total Received]] - Table1[[#This Row],[Total Sold]] -> 5 | M64: 1 | N64: 46563 | O64: =IF(Table1[[#This Row],[Current Stock]] <= Table1[[#This Row],[Min Stock]], "REORDER NOW", "Good") -> Good | P64: =(Table1[[#This Row],[Unit Price]] - Table1[[#This Row],[Cost Per Pc]]) * Table1[[#This Row],[Total Sold]] -> 0 | R64: =(Table1[[#This Row],[Total Received]] / Table1[[#This Row],[Pcs per Box]]) * Table1[[#This Row],[Cost Price]] -> 660 | S64: =SUM($R$3:Table1[[#This Row],[Annual Consumption Value]]) / SUM(Table1[Annual Consumption Value]) -> 0.55207361 | T64: =IF(Table1[[#This Row],[Cumulative %]]<=0.8, "A", IF(Table1[[#This Row],[Cumulative %]]<=0.95, "B", "C")) -> A
A65: GA-001 | B65: Losectil 20 | C65: Omeprazole | D65: Capsule | E65: Gastric & Duodenal Ulcer | F65: 1584.1 | G65: 360 | H65: =Table1[[#This Row],[Cost Price]]/Table1[[#This Row],[Pcs per Box]] -> 4.4002778 | I65: 5 | J65: =SUMIF('Stock In'!C:C, Table1[[#This Row],[Medicine ID]], 'Stock In'!E:E) * Table1[[#This Row],[Pcs per Box]] -> 2160 | K65: =SUMIF('Sales Log Table'!C:C, Table1[[#This Row],[Medicine ID]], 'Sales Log Table'!E:E) -> 0 | L65: =Table1[[#This Row],[Total Received]] - Table1[[#This Row],[Total Sold]] -> 2160 | M65: 1200 | N65: 46563 | O65: =IF(Table1[[#This Row],[Current Stock]] <= Table1[[#This Row],[Min Stock]], "REORDER NOW", "Good") -> Good | P65: =(Table1[[#This Row],[Unit Price]] - Table1[[#This Row],[Cost Per Pc]]) * Table1[[#This Row],[Total Sold]] -> 0 | R65: =(Table1[[#This Row],[Total Received]] / Table1[[#This Row],[Pcs per Box]]) * Table1[[#This Row],[Cost Price]] -> 9504.6 | S65: =SUM($R$3:Table1[[#This Row],[Annual Consumption Value]]) / SUM(Table1[Annual Consumption Value]) -> 0.5869748 | T65: =IF(Table1[[#This Row],[Cumulative %]]<=0.8, "A", IF(Table1[[#This Row],[Cumulative %]]<=0.95, "B", "C")) -> A
A66: GA-002 | B66: Losectil 40 | C66: Omeprazole | D66: Capsule | E66: Gastric & Duodenal Ulcer | F66: 352.02 | G66: 40 | H66: =Table1[[#This Row],[Cost Price]]/Table1[[#This Row],[Pcs per Box]] -> 8.8005 | I66: 10 | J66: =SUMIF('Stock In'!C:C, Table1[[#This Row],[Medicine ID]], 'Stock In'!E:E) * Table1[[#This Row],[Pcs per Box]] -> 200 | K66: =SUMIF('Sales Log Table'!C:C, Table1[[#This Row],[Medicine ID]], 'Sales Log Table'!E:E) -> 0 | L66: =Table1[[#This Row],[Total Received]] - Table1[[#This Row],[Total Sold]] -> 200 | N66: 46563 | O66: =IF(Table1[[#This Row],[Current Stock]] <= Table1[[#This Row],[Min Stock]], "REORDER NOW", "Good") -> Good | P66: =(Table1[[#This Row],[Unit Price]] - Table1[[#This Row],[Cost Per Pc]]) * Table1[[#This Row],[Total Sold]] -> 0 | R66: =(Table1[[#This Row],[Total Received]] / Table1[[#This Row],[Pcs per Box]]) * Table1[[#This Row],[Cost Price]] -> 1760.1 | S66: =SUM($R$3:Table1[[#This Row],[Annual Consumption Value]]) / SUM(Table1[Annual Consumption Value]) -> 0.59343794 | T66: =IF(Table1[[#This Row],[Cumulative %]]<=0.8, "A", IF(Table1[[#This Row],[Cumulative %]]<=0.95, "B", "C")) -> A
A67: GA-003 | B67: Seclo | C67: Omeprazole | D67: Capsule | E67: Gastric & Duodenal Ulcer | F67: =(Table1[[#This Row],[Unit Price]] * 0.9) * Table1[[#This Row],[Pcs per Box]] -> 648 | G67: 120 | H67: =Table1[[#This Row],[Cost Price]]/Table1[[#This Row],[Pcs per Box]] -> 5.4 | I67: 6 | J67: =SUMIF('Stock In'!C:C, Table1[[#This Row],[Medicine ID]], 'Stock In'!E:E) * Table1[[#This Row],[Pcs per Box]] -> 840 | K67: =SUMIF('Sales Log Table'!C:C, Table1[[#This Row],[Medicine ID]], 'Sales Log Table'!E:E) -> 20 | L67: =Table1[[#This Row],[Total Received]] - Table1[[#This Row],[Total Sold]] -> 820 | M67: 360 | N67: 46563 | O67: =IF(Table1[[#This Row],[Current Stock]] <= Table1[[#This Row],[Min Stock]], "REORDER NOW", "Good") -> Good | P67: =(Table1[[#This Row],[Unit Price]] - Table1[[#This Row],[Cost Per Pc]]) * Table1[[#This Row],[Total Sold]] -> 12 | R67: =(Table1[[#This Row],[Total Received]] / Table1[[#This Row],[Pcs per Box]]) * Table1[[#This Row],[Cost Price]] -> 4536 | S67: =SUM($R$3:Table1[[#This Row],[Annual Consumption Value]]) / SUM(Table1[Annual Consumption Value]) -> 0.61009427 | T67: =IF(Table1[[#This Row],[Cumulative %]]<=0.8, "A", IF(Table1[[#This Row],[Cumulative %]]<=0.95, "B", "C")) -> A
A68: GA-004 | B68: Exium | C68: Esomeprazole | D68: Capsule | E68: Duodenal & Gastric ulcer | F68: =(Table1[[#This Row],[Unit Price]] * 0.9) * Table1[[#This Row],[Pcs per Box]] -> 810 | G68: 100 | H68: =Table1[[#This Row],[Cost Price]]/Table1[[#This Row],[Pcs per Box]] -> 8.1 | I68: 9 | J68: =SUMIF('Stock In'!C:C, Table1[[#This Row],[Medicine ID]], 'Stock In'!E:E) * Table1[[#This Row],[Pcs per Box]] -> 400 | K68: =SUMIF('Sales Log Table'!C:C, Table1[[#This Row],[Medicine ID]], 'Sales Log Table'!E:E) -> 10 | L68: =Table1[[#This Row],[Total Received]] - Table1[[#This Row],[Total Sold]] -> 390 | M68: 140 | N68: 46563 | O68: =IF(Table1[[#This Row],[Current Stock]] <= Table1[[#This Row],[Min Stock]], "REORDER NOW", "Good") -> Good | P68: =(Table1[[#This Row],[Unit Price]] - Table1[[#This Row],[Cost Per Pc]]) * Table1[[#This Row],[Total Sold]] -> 9 | R68: =(Table1[[#This Row],[Total Received]] / Table1[[#This Row],[Pcs per Box]]) * Table1[[#This Row],[Cost Price]] -> 3240 | S68: =SUM($R$3:Table1[[#This Row],[Annual Consumption Value]]) / SUM(Table1[Annual Consumption Value]) -> 0.62199166 | T68: =IF(Table1[[#This Row],[Cumulative %]]<=0.8, "A", IF(Table1[[#This Row],[Cumulative %]]<=0.95, "B", "C")) -> A
A69: GA-005 | B69: Maxpro 20mg | C69: Esomeprazole | D69: Capsule | E69: Duodenal & Gastric ulcer | F69: 863 | G69: 140 | H69: =Table1[[#This Row],[Cost Price]]/Table1[[#This Row],[Pcs per Box]] -> 6.1642857 | I69: 7 | J69: =SUMIF('Stock In'!C:C, Table1[[#This Row],[Medicine ID]], 'Stock In'!E:E) * Table1[[#This Row],[Pcs per Box]] -> 980 | K69: =SUMIF('Sales Log Table'!C:C, Table1[[#This Row],[Medicine ID]], 'Sales Log Table'!E:E) -> 14 | L69: =Table1[[#This Row],[Total Received]] - Table1[[#This Row],[Total Sold]] -> 966 | M69: 600 | N69: 46563 | O69: =IF(Table1[[#This Row],[Current Stock]] <= Table1[[#This Row],[Min Stock]], "REORDER NOW", "Good") -> Good | P69: =(Table1[[#This Row],[Unit Price]] - Table1[[#This Row],[Cost Per Pc]]) * Table1[[#This Row],[Total Sold]] -> 11.7 | R69: =(Table1[[#This Row],[Total Received]] / Table1[[#This Row],[Pcs per Box]]) * Table1[[#This Row],[Cost Price]] -> 6041 | S69: =SUM($R$3:Table1[[#This Row],[Annual Consumption Value]]) / SUM(Table1[Annual Consumption Value]) -> 0.6441744 | T69: =IF(Table1[[#This Row],[Cumulative %]]<=0.8, "A", IF(Table1[[#This Row],[Cumulative %]]<=0.95, "B", "C")) -> A
A70: GA-006 | B70: Esoral | C70: Esomeprazole | D70: Capsule | E70: Duodenal & Gastric ulcer | F70: =(Table1[[#This Row],[Unit Price]] * 0.9) * Table1[[#This Row],[Pcs per Box]] -> 630 | G70: 100 | H70: =Table1[[#This Row],[Cost Price]]/Table1[[#This Row],[Pcs per Box]] -> 6.3 | I70: 7 | J70: =SUMIF('Stock In'!C:C, Table1[[#This Row],[Medicine ID]], 'Stock In'!E:E) * Table1[[#This Row],[Pcs per Box]] -> 400 | K70: =SUMIF('Sales Log Table'!C:C, Table1[[#This Row],[Medicine ID]], 'Sales Log Table'!E:E) -> 0 | L70: =Table1[[#This Row],[Total Received]] - Table1[[#This Row],[Total Sold]] -> 400 | M70: 100 | N70: 46563 | O70: =IF(Table1[[#This Row],[Current Stock]] <= Table1[[#This Row],[Min Stock]], "REORDER NOW", "Good") -> Good | P70: =(Table1[[#This Row],[Unit Price]] - Table1[[#This Row],[Cost Per Pc]]) * Table1[[#This Row],[Total Sold]] -> 0 | R70: =(Table1[[#This Row],[Total Received]] / Table1[[#This Row],[Pcs per Box]]) * Table1[[#This Row],[Cost Price]] -> 2520 | S70: =SUM($R$3:Table1[[#This Row],[Annual Consumption Value]]) / SUM(Table1[Annual Consumption Value]) -> 0.65342792 | T70: =IF(Table1[[#This Row],[Cumulative %]]<=0.8, "A", IF(Table1[[#This Row],[Cumulative %]]<=0.95, "B", "C")) -> A
A71: GA-007 | B71: Progut 20 | C71: Esomeprazole | D71: Capsule | E71: Duodenal & Gastric ulcer | F71: 704.05 | G71: 100 | H71: =Table1[[#This Row],[Cost Price]]/Table1[[#This Row],[Pcs per Box]] -> 7.0405 | I71: 8 | J71: =SUMIF('Stock In'!C:C, Table1[[#This Row],[Medicine ID]], 'Stock In'!E:E) * Table1[[#This Row],[Pcs per Box]] -> 600 | K71: =SUMIF('Sales Log Table'!C:C, Table1[[#This Row],[Medicine ID]], 'Sales Log Table'!E:E) -> 0 | L71: =Table1[[#This Row],[Total Received]] - Table1[[#This Row],[Total Sold]] -> 600 | M71: 140 | N71: 46563 | O71: =IF(Table1[[#This Row],[Current Stock]] <= Table1[[#This Row],[Min Stock]], "REORDER NOW", "Good") -> Good | P71: =(Table1[[#This Row],[Unit Price]] - Table1[[#This Row],[Cost Per Pc]]) * Table1[[#This Row],[Total Sold]] -> 0 | R71: =(Table1[[#This Row],[Total Received]] / Table1[[#This Row],[Pcs per Box]]) * Table1[[#This Row],[Cost Price]] -> 4224.3 | S71: =SUM($R$3:Table1[[#This Row],[Annual Consumption Value]]) / SUM(Table1[Annual Consumption Value]) -> 0.66893968 | T71: =IF(Table1[[#This Row],[Cumulative %]]<=0.8, "A", IF(Table1[[#This Row],[Cumulative %]]<=0.95, "B", "C")) -> A
A72: GA-008 | B72: Maxpro MUPS 20mg | C72: Esomeprazole | D72: Tablet | E72: Gastroesophageal reflux disease (GERD) | F72: 616.35 | G72: 70 | H72: =Table1[[#This Row],[Cost Price]]/Table1[[#This Row],[Pcs per Box]] -> 8.805 | I72: 10 | J72: =SUMIF('Stock In'!C:C, Table1[[#This Row],[Medicine ID]], 'Stock In'!E:E) * Table1[[#This Row],[Pcs per Box]] -> 770 | K72: =SUMIF('Sales Log Table'!C:C, Table1[[#This Row],[Medicine ID]], 'Sales Log Table'!E:E) -> 0 | L72: =Table1[[#This Row],[Total Received]] - Table1[[#This Row],[Total Sold]] -> 770 | M72: 550 | N72: 46563 | O72: =IF(Table1[[#This Row],[Current Stock]] <= Table1[[#This Row],[Min Stock]], "REORDER NOW", "Good") -> Good | P72: =(Table1[[#This Row],[Unit Price]] - Table1[[#This Row],[Cost Per Pc]]) * Table1[[#This Row],[Total Sold]] -> 0 | R72: =(Table1[[#This Row],[Total Received]] / Table1[[#This Row],[Pcs per Box]]) * Table1[[#This Row],[Cost Price]] -> 6779.85 | S72: =SUM($R$3:Table1[[#This Row],[Annual Consumption Value]]) / SUM(Table1[Annual Consumption Value]) -> 0.6938355 | T72: =IF(Table1[[#This Row],[Cumulative %]]<=0.8, "A", IF(Table1[[#This Row],[Cumulative %]]<=0.95, "B", "C")) -> A
A73: GA-009 | B73: Progut MUPS | C73: Esomeprazole | D73: Tablet | E73: Gastroesophageal reflux disease (GERD) | F73: =(Table1[[#This Row],[Unit Price]] * 0.9) * Table1[[#This Row],[Pcs per Box]] -> 495 | G73: 50 | H73: =Table1[[#This Row],[Cost Price]]/Table1[[#This Row],[Pcs per Box]] -> 9.9 | I73: 11 | J73: =SUMIF('Stock In'!C:C, Table1[[#This Row],[Medicine ID]], 'Stock In'!E:E) * Table1[[#This Row],[Pcs per Box]] -> 200 | K73: =SUMIF('Sales Log Table'!C:C, Table1[[#This Row],[Medicine ID]], 'Sales Log Table'!E:E) -> 0 | L73: =Table1[[#This Row],[Total Received]] - Table1[[#This Row],[Total Sold]] -> 200 | M73: 50 | N73: 46563 | O73: =IF(Table1[[#This Row],[Current Stock]] <= Table1[[#This Row],[Min Stock]], "REORDER NOW", "Good") -> Good | P73: =(Table1[[#This Row],[Unit Price]] - Table1[[#This Row],[Cost Per Pc]]) * Table1[[#This Row],[Total Sold]] -> 0 | R73: =(Table1[[#This Row],[Total Received]] / Table1[[#This Row],[Pcs per Box]]) * Table1[[#This Row],[Cost Price]] -> 1980 | S73: =SUM($R$3:Table1[[#This Row],[Annual Consumption Value]]) / SUM(Table1[Annual Consumption Value]) -> 0.70110612 | T73: =IF(Table1[[#This Row],[Cumulative %]]<=0.8, "A", IF(Table1[[#This Row],[Cumulative %]]<=0.95, "B", "C")) -> A
A74: GA-010 | B74: Othera 20 | C74: Esomeprazole | D74: Tablet | E74: Gastroesophageal reflux disease (GERD) | F74: =(Table1[[#This Row],[Unit Price]] * 0.9) * Table1[[#This Row],[Pcs per Box]] -> 594 | G74: 60 | H74: =Table1[[#This Row],[Cost Price]]/Table1[[#This Row],[Pcs per Box]] -> 9.9 | I74: 11 | J74: =SUMIF('Stock In'!C:C, Table1[[#This Row],[Medicine ID]], 'Stock In'!E:E) * Table1[[#This Row],[Pcs per Box]] -> 780 | K74: =SUMIF('Sales Log Table'!C:C, Table1[[#This Row],[Medicine ID]], 'Sales Log Table'!E:E) -> 0 | L74: =Table1[[#This Row],[Total Received]] - Table1[[#This Row],[Total Sold]] -> 780 | M74: 400 | N74: 46563 | O74: =IF(Table1[[#This Row],[Current Stock]] <= Table1[[#This Row],[Min Stock]], "REORDER NOW", "Good") -> Good | P74: =(Table1[[#This Row],[Unit Price]] - Table1[[#This Row],[Cost Per Pc]]) * Table1[[#This Row],[Total Sold]] -> 0 | R74: =(Table1[[#This Row],[Total Received]] / Table1[[#This Row],[Pcs per Box]]) * Table1[[#This Row],[Cost Price]] -> 7722 | S74: =SUM($R$3:Table1[[#This Row],[Annual Consumption Value]]) / SUM(Table1[Annual Consumption Value]) -> 0.72946155 | T74: =IF(Table1[[#This Row],[Cumulative %]]<=0.8, "A", IF(Table1[[#This Row],[Cumulative %]]<=0.95, "B", "C")) -> A
A75: GA-011 | B75: Don-A | C75: Domperidone | D75: Tablet | E75: Motility / Gastric helper | F75: =(Table1[[#This Row],[Unit Price]] * 0.9) * Table1[[#This Row],[Pcs per Box]] -> 434.7 | G75: 140 | H75: =Table1[[#This Row],[Cost Price]]/Table1[[#This Row],[Pcs per Box]] -> 3.105 | I75: 3.45 | J75: =SUMIF('Stock In'!C:C, Table1[[#This Row],[Medicine ID]], 'Stock In'!E:E) * Table1[[#This Row],[Pcs per Box]] -> 420 | K75: =SUMIF('Sales Log Table'!C:C, Table1[[#This Row],[Medicine ID]], 'Sales Log Table'!E:E) -> 0 | L75: =Table1[[#This Row],[Total Received]] - Table1[[#This Row],[Total Sold]] -> 420 | M75: 200 | N75: 46563 | O75: =IF(Table1[[#This Row],[Current Stock]] <= Table1[[#This Row],[Min Stock]], "REORDER NOW", "Good") -> Good | P75: =(Table1[[#This Row],[Unit Price]] - Table1[[#This Row],[Cost Per Pc]]) * Table1[[#This Row],[Total Sold]] -> 0 | R75: =(Table1[[#This Row],[Total Received]] / Table1[[#This Row],[Pcs per Box]]) * Table1[[#This Row],[Cost Price]] -> 1304.1 | S75: =SUM($R$3:Table1[[#This Row],[Annual Consumption Value]]) / SUM(Table1[Annual Consumption Value]) -> 0.73425024 | T75: =IF(Table1[[#This Row],[Cumulative %]]<=0.8, "A", IF(Table1[[#This Row],[Cumulative %]]<=0.95, "B", "C")) -> A
A76: GA-012 | B76: Sandom | C76: Domperidone | D76: Tablet | E76: Motility / Gastric helper | F76: =(Table1[[#This Row],[Unit Price]] * 0.9) * Table1[[#This Row],[Pcs per Box]] -> 181.8 | G76: 100 | H76: =Table1[[#This Row],[Cost Price]]/Table1[[#This Row],[Pcs per Box]] -> 1.818 | I76: 2.02 | J76: =SUMIF('Stock In'!C:C, Table1[[#This Row],[Medicine ID]], 'Stock In'!E:E) * Table1[[#This Row],[Pcs per Box]] -> 200 | K76: =SUMIF('Sales Log Table'!C:C, Table1[[#This Row],[Medicine ID]], 'Sales Log Table'!E:E) -> 0 | L76: =Table1[[#This Row],[Total Received]] - Table1[[#This Row],[Total Sold]] -> 200 | M76: 100 | N76: 46563 | O76: =IF(Table1[[#This Row],[Current Stock]] <= Table1[[#This Row],[Min Stock]], "REORDER NOW", "Good") -> Good | P76: =(Table1[[#This Row],[Unit Price]] - Table1[[#This Row],[Cost Per Pc]]) * Table1[[#This Row],[Total Sold]] -> 0 | R76: =(Table1[[#This Row],[Total Received]] / Table1[[#This Row],[Pcs per Box]]) * Table1[[#This Row],[Cost Price]] -> 363.6 | S76: =SUM($R$3:Table1[[#This Row],[Annual Consumption Value]]) / SUM(Table1[Annual Consumption Value]) -> 0.7355854 | T76: =IF(Table1[[#This Row],[Cumulative %]]<=0.8, "A", IF(Table1[[#This Row],[Cumulative %]]<=0.95, "B", "C")) -> A
A77: GA-013 | B77: Deflux | C77: Domperidone | D77: Tablet | E77: Motility / Gastric helper | F77: =(Table1[[#This Row],[Unit Price]] * 0.9) * Table1[[#This Row],[Pcs per Box]] -> 540 | G77: 150 | H77: =Table1[[#This Row],[Cost Price]]/Table1[[#This Row],[Pcs per Box]] -> 3.6 | I77: 4 | J77: =SUMIF('Stock In'!C:C, Table1[[#This Row],[Medicine ID]], 'Stock In'!E:E) * Table1[[#This Row],[Pcs per Box]] -> 900 | K77: =SUMIF('Sales Log Table'!C:C, Table1[[#This Row],[Medicine ID]], 'Sales Log Table'!E:E) -> 0 | L77: =Table1[[#This Row],[Total Received]] - Table1[[#This Row],[Total Sold]] -> 900 | M77: 150 | N77: 46563 | O77: =IF(Table1[[#This Row],[Current Stock]] <= Table1[[#This Row],[Min Stock]], "REORDER NOW", "Good") -> Good | P77: =(Table1[[#This Row],[Unit Price]] - Table1[[#This Row],[Cost Per Pc]]) * Table1[[#This Row],[Total Sold]] -> 0 | R77: =(Table1[[#This Row],[Total Received]] / Table1[[#This Row],[Pcs per Box]]) * Table1[[#This Row],[Cost Price]] -> 3240 | S77: =SUM($R$3:Table1[[#This Row],[Annual Consumption Value]]) / SUM(Table1[Annual Consumption Value]) -> 0.74748278 | T77: =IF(Table1[[#This Row],[Cumulative %]]<=0.8, "A", IF(Table1[[#This Row],[Cumulative %]]<=0.95, "B", "C")) -> A
A78: GA-014 | B78: Omidon | C78: Domperidone | D78: Tablet | E78: Motility / Gastric helper | F78: =(Table1[[#This Row],[Unit Price]] * 0.9) * Table1[[#This Row],[Pcs per Box]] -> 472.5 | G78: 150 | H78: =Table1[[#This Row],[Cost Price]]/Table1[[#This Row],[Pcs per Box]] -> 3.15 | I78: 3.5 | J78: =SUMIF('Stock In'!C:C, Table1[[#This Row],[Medicine ID]], 'Stock In'!E:E) * Table1[[#This Row],[Pcs per Box]] -> 150 | K78: =SUMIF('Sales Log Table'!C:C, Table1[[#This Row],[Medicine ID]], 'Sales Log Table'!E:E) -> 0 | L78: =Table1[[#This Row],[Total Received]] - Table1[[#This Row],[Total Sold]] -> 150 | M78: 20 | N78: 46563 | O78: =IF(Table1[[#This Row],[Current Stock]] <= Table1[[#This Row],[Min Stock]], "REORDER NOW", "Good") -> Good | P78: =(Table1[[#This Row],[Unit Price]] - Table1[[#This Row],[Cost Per Pc]]) * Table1[[#This Row],[Total Sold]] -> 0 | R78: =(Table1[[#This Row],[Total Received]] / Table1[[#This Row],[Pcs per Box]]) * Table1[[#This Row],[Cost Price]] -> 472.5 | S78: =SUM($R$3:Table1[[#This Row],[Annual Consumption Value]]) / SUM(Table1[Annual Consumption Value]) -> 0.74921781 | T78: =IF(Table1[[#This Row],[Cumulative %]]<=0.8, "A", IF(Table1[[#This Row],[Cumulative %]]<=0.95, "B", "C")) -> A
A79: GA-015 | B79: Zofra 50ml | C79: Ondansetron | D79: Oral Solution | E79: Anti-vomiting / Nausea | F79: 44 | G79: 1 | H79: =Table1[[#This Row],[Cost Price]]/Table1[[#This Row],[Pcs per Box]] -> 44 | I79: 50 | J79: =SUMIF('Stock In'!C:C, Table1[[#This Row],[Medicine ID]], 'Stock In'!E:E) * Table1[[#This Row],[Pcs per Box]] -> 11 | K79: =SUMIF('Sales Log Table'!C:C, Table1[[#This Row],[Medicine ID]], 'Sales Log Table'!E:E) -> 0 | L79: =Table1[[#This Row],[Total Received]] - Table1[[#This Row],[Total Sold]] -> 11 | M79: 1 | N79: 46563 | O79: =IF(Table1[[#This Row],[Current Stock]] <= Table1[[#This Row],[Min Stock]], "REORDER NOW", "Good") -> Good | P79: =(Table1[[#This Row],[Unit Price]] - Table1[[#This Row],[Cost Per Pc]]) * Table1[[#This Row],[Total Sold]] -> 0 | R79: =(Table1[[#This Row],[Total Received]] / Table1[[#This Row],[Pcs per Box]]) * Table1[[#This Row],[Cost Price]] -> 484 | S79: =SUM($R$3:Table1[[#This Row],[Annual Consumption Value]]) / SUM(Table1[Annual Consumption Value]) -> 0.75099507 | T79: =IF(Table1[[#This Row],[Cumulative %]]<=0.8, "A", IF(Table1[[#This Row],[Cumulative %]]<=0.95, "B", "C")) -> A
A80: GA-016 | B80: Zofra ODT 8mg | C80: Ondansetron | D80: Tablet | E80: Anti-vomiting / Nausea | F80: 425.07 | G80: 42 | H80: =Table1[[#This Row],[Cost Price]]/Table1[[#This Row],[Pcs per Box]] -> 10.120714 | I80: 11.5 | J80: =SUMIF('Stock In'!C:C, Table1[[#This Row],[Medicine ID]], 'Stock In'!E:E) * Table1[[#This Row],[Pcs per Box]] -> 42 | K80: =SUMIF('Sales Log Table'!C:C, Table1[[#This Row],[Medicine ID]], 'Sales Log Table'!E:E) -> 0 | L80: =Table1[[#This Row],[Total Received]] - Table1[[#This Row],[Total Sold]] -> 42 | M80: 14 | N80: 46563 | O80: =IF(Table1[[#This Row],[Current Stock]] <= Table1[[#This Row],[Min Stock]], "REORDER NOW", "Good") -> Good | P80: =(Table1[[#This Row],[Unit Price]] - Table1[[#This Row],[Cost Per Pc]]) * Table1[[#This Row],[Total Sold]] -> 0 | R80: =(Table1[[#This Row],[Total Received]] / Table1[[#This Row],[Pcs per Box]]) * Table1[[#This Row],[Cost Price]] -> 425.07 | S80: =SUM($R$3:Table1[[#This Row],[Annual Consumption Value]]) / SUM(Table1[Annual Consumption Value]) -> 0.75255594 | T80: =IF(Table1[[#This Row],[Cumulative %]]<=0.8, "A", IF(Table1[[#This Row],[Cumulative %]]<=0.95, "B", "C")) -> A
A81: GA-017 | B81: DDR 30mg | C81: Dexlansoprazole | D81: Capsule | E81: Antacid / Anti-ulcer | F81: 607.2 | G81: 60 | H81: =Table1[[#This Row],[Cost Price]]/Table1[[#This Row],[Pcs per Box]] -> 10.12 | I81: 11.5 | J81: =SUMIF('Stock In'!C:C, Table1[[#This Row],[Medicine ID]], 'Stock In'!E:E) * Table1[[#This Row],[Pcs per Box]] -> 60 | K81: =SUMIF('Sales Log Table'!C:C, Table1[[#This Row],[Medicine ID]], 'Sales Log Table'!E:E) -> 0 | L81: =Table1[[#This Row],[Total Received]] - Table1[[#This Row],[Total Sold]] -> 60 | M81: 10 | N81: 46563 | O81: =IF(Table1[[#This Row],[Current Stock]] <= Table1[[#This Row],[Min Stock]], "REORDER NOW", "Good") -> Good | P81: =(Table1[[#This Row],[Unit Price]] - Table1[[#This Row],[Cost Per Pc]]) * Table1[[#This Row],[Total Sold]] -> 0 | R81: =(Table1[[#This Row],[Total Received]] / Table1[[#This Row],[Pcs per Box]]) * Table1[[#This Row],[Cost Price]] -> 607.2 | S81: =SUM($R$3:Table1[[#This Row],[Annual Consumption Value]]) / SUM(Table1[Annual Consumption Value]) -> 0.7547856 | T81: =IF(Table1[[#This Row],[Cumulative %]]<=0.8, "A", IF(Table1[[#This Row],[Cumulative %]]<=0.95, "B", "C")) -> A
A82: GA-018 | B82: Dantron 8mg | C82: Ondansetron | D82: Tablet | E82: Anti-vomiting / Nausea | F82: 290.42 | G82: 30 | H82: =Table1[[#This Row],[Cost Price]]/Table1[[#This Row],[Pcs per Box]] -> 9.6806667 | I82: 11 | J82: =SUMIF('Stock In'!C:C, Table1[[#This Row],[Medicine ID]], 'Stock In'!E:E) * Table1[[#This Row],[Pcs per Box]] -> 180 | K82: =SUMIF('Sales Log Table'!C:C, Table1[[#This Row],[Medicine ID]], 'Sales Log Table'!E:E) -> 0 | L82: =Table1[[#This Row],[Total Received]] - Table1[[#This Row],[Total Sold]] -> 180 | O82: =IF(Table1[[#This Row],[Current Stock]] <= Table1[[#This Row],[Min Stock]], "REORDER NOW", "Good") -> Good | P82: =(Table1[[#This Row],[Unit Price]] - Table1[[#This Row],[Cost Per Pc]]) * Table1[[#This Row],[Total Sold]] -> 0 | R82: =(Table1[[#This Row],[Total Received]] / Table1[[#This Row],[Pcs per Box]]) * Table1[[#This Row],[Cost Price]] -> 1742.52 | S82: =SUM($R$3:Table1[[#This Row],[Annual Consumption Value]]) / SUM(Table1[Annual Consumption Value]) -> 0.76118419 | T82: =IF(Table1[[#This Row],[Cumulative %]]<=0.8, "A", IF(Table1[[#This Row],[Cumulative %]]<=0.95, "B", "C")) -> A
A83: GA-019 | B83: Algin 50mg | C83: Tiemonium Methylsulfate | D83: Tablet | E83: Anti-abdominal / Menstrual Cramps | F83: 747.85 | G83: 100 | H83: =Table1[[#This Row],[Cost Price]]/Table1[[#This Row],[Pcs per Box]] -> 7.4785 | I83: 8.5 | J83: =SUMIF('Stock In'!C:C, Table1[[#This Row],[Medicine ID]], 'Stock In'!E:E) * Table1[[#This Row],[Pcs per Box]] -> 200 | K83: =SUMIF('Sales Log Table'!C:C, Table1[[#This Row],[Medicine ID]], 'Sales Log Table'!E:E) -> 0 | L83: =Table1[[#This Row],[Total Received]] - Table1[[#This Row],[Total Sold]] -> 200 | O83: =IF(Table1[[#This Row],[Current Stock]] <= Table1[[#This Row],[Min Stock]], "REORDER NOW", "Good") -> Good | P83: =(Table1[[#This Row],[Unit Price]] - Table1[[#This Row],[Cost Per Pc]]) * Table1[[#This Row],[Total Sold]] -> 0 | R83: =(Table1[[#This Row],[Total Received]] / Table1[[#This Row],[Pcs per Box]]) * Table1[[#This Row],[Cost Price]] -> 1495.7 | S83: =SUM($R$3:Table1[[#This Row],[Annual Consumption Value]]) / SUM(Table1[Annual Consumption Value]) -> 0.76667645 | T83: =IF(Table1[[#This Row],[Cumulative %]]<=0.8, "A", IF(Table1[[#This Row],[Cumulative %]]<=0.95, "B", "C")) -> A
A84: GA-020 | B84: Maxpro EC 20mg | C84: Esomeprazole | D84: Tablet | E84: Duodenal & Gastric ulcer | F84: 863 | G84: 140 | H84: =Table1[[#This Row],[Cost Price]]/Table1[[#This Row],[Pcs per Box]] -> 6.1642857 | I84: 7 | J84: =SUMIF('Stock In'!C:C, Table1[[#This Row],[Medicine ID]], 'Stock In'!E:E) * Table1[[#This Row],[Pcs per Box]] -> 140 | K84: =SUMIF('Sales Log Table'!C:C, Table1[[#This Row],[Medicine ID]], 'Sales Log Table'!E:E) -> 0 | L84: =Table1[[#This Row],[Total Received]] - Table1[[#This Row],[Total Sold]] -> 140 | O84: =IF(Table1[[#This Row],[Current Stock]] <= Table1[[#This Row],[Min Stock]], "REORDER NOW", "Good") -> Good | P84: =(Table1[[#This Row],[Unit Price]] - Table1[[#This Row],[Cost Per Pc]]) * Table1[[#This Row],[Total Sold]] -> 0 | R84: =(Table1[[#This Row],[Total Received]] / Table1[[#This Row],[Pcs per Box]]) * Table1[[#This Row],[Cost Price]] -> 863 | S84: =SUM($R$3:Table1[[#This Row],[Annual Consumption Value]]) / SUM(Table1[Annual Consumption Value]) -> 0.76984541 | T84: =IF(Table1[[#This Row],[Cumulative %]]<=0.8, "A", IF(Table1[[#This Row],[Cumulative %]]<=0.95, "B", "C")) -> A
A85: GA-021 | B85: Maxpro MUPS 40mg | C85: Esomeprazole | D85: Tablet | E85: Duodenal & Gastric ulcer | F85: 660 | G85: 50 | H85: =Table1[[#This Row],[Cost Price]]/Table1[[#This Row],[Pcs per Box]] -> 13.2 | I85: 15 | J85: =SUMIF('Stock In'!C:C, Table1[[#This Row],[Medicine ID]], 'Stock In'!E:E) * Table1[[#This Row],[Pcs per Box]] -> 50 | K85: =SUMIF('Sales Log Table'!C:C, Table1[[#This Row],[Medicine ID]], 'Sales Log Table'!E:E) -> 0 | L85: =Table1[[#This Row],[Total Received]] - Table1[[#This Row],[Total Sold]] -> 50 | O85: =IF(Table1[[#This Row],[Current Stock]] <= Table1[[#This Row],[Min Stock]], "REORDER NOW", "Good") -> Good | P85: =(Table1[[#This Row],[Unit Price]] - Table1[[#This Row],[Cost Per Pc]]) * Table1[[#This Row],[Total Sold]] -> 0 | R85: =(Table1[[#This Row],[Total Received]] / Table1[[#This Row],[Pcs per Box]]) * Table1[[#This Row],[Cost Price]] -> 660 | S85: =SUM($R$3:Table1[[#This Row],[Annual Consumption Value]]) / SUM(Table1[Annual Consumption Value]) -> 0.77226895 | T85: =IF(Table1[[#This Row],[Cumulative %]]<=0.8, "A", IF(Table1[[#This Row],[Cumulative %]]<=0.95, "B", "C")) -> A
A86: NE-001 | B86: Anzet | C86: Flupentixol + Melitracen | D86: Tablet | E86: Neuro / Anti-anxiety | F86: 440.03 | G86: 100 | H86: =Table1[[#This Row],[Cost Price]]/Table1[[#This Row],[Pcs per Box]] -> 4.4003 | I86: 5 | J86: =SUMIF('Stock In'!C:C, Table1[[#This Row],[Medicine ID]], 'Stock In'!E:E) * Table1[[#This Row],[Pcs per Box]] -> 500 | K86: =SUMIF('Sales Log Table'!C:C, Table1[[#This Row],[Medicine ID]], 'Sales Log Table'!E:E) -> 10 | L86: =Table1[[#This Row],[Total Received]] - Table1[[#This Row],[Total Sold]] -> 490 | M86: 50 | N86: 46563 | O86: =IF(Table1[[#This Row],[Current Stock]] <= Table1[[#This Row],[Min Stock]], "REORDER NOW", "Good") -> Good | P86: =(Table1[[#This Row],[Unit Price]] - Table1[[#This Row],[Cost Per Pc]]) * Table1[[#This Row],[Total Sold]] -> 5.997 | R86: =(Table1[[#This Row],[Total Received]] / Table1[[#This Row],[Pcs per Box]]) * Table1[[#This Row],[Cost Price]] -> 2200.15 | S86: =SUM($R$3:Table1[[#This Row],[Annual Consumption Value]]) / SUM(Table1[Annual Consumption Value]) -> 0.78034797 | T86: =IF(Table1[[#This Row],[Cumulative %]]<=0.8, "A", IF(Table1[[#This Row],[Cumulative %]]<=0.95, "B", "C")) -> A
A87: NE-002 | B87: Anfree | C87: Flupentixol + Melitracen | D87: Tablet | E87: Neuro / Anti-anxiety | F87: =(Table1[[#This Row],[Unit Price]] * 0.9) * Table1[[#This Row],[Pcs per Box]] -> 450 | G87: 100 | H87: =Table1[[#This Row],[Cost Price]]/Table1[[#This Row],[Pcs per Box]] -> 4.5 | I87: 5 | J87: =SUMIF('Stock In'!C:C, Table1[[#This Row],[Medicine ID]], 'Stock In'!E:E) * Table1[[#This Row],[Pcs per Box]] -> 200 | K87: =SUMIF('Sales Log Table'!C:C, Table1[[#This Row],[Medicine ID]], 'Sales Log Table'!E:E) -> 0 | L87: =Table1[[#This Row],[Total Received]] - Table1[[#This Row],[Total Sold]] -> 200 | M87: 100 | N87: 46563 | O87: =IF(Table1[[#This Row],[Current Stock]] <= Table1[[#This Row],[Min Stock]], "REORDER NOW", "Good") -> Good | P87: =(Table1[[#This Row],[Unit Price]] - Table1[[#This Row],[Cost Per Pc]]) * Table1[[#This Row],[Total Sold]] -> 0 | R87: =(Table1[[#This Row],[Total Received]] / Table1[[#This Row],[Pcs per Box]]) * Table1[[#This Row],[Cost Price]] -> 900 | S87: =SUM($R$3:Table1[[#This Row],[Annual Consumption Value]]) / SUM(Table1[Annual Consumption Value]) -> 0.7836528 | T87: =IF(Table1[[#This Row],[Cumulative %]]<=0.8, "A", IF(Table1[[#This Row],[Cumulative %]]<=0.95, "B", "C")) -> A
A88: NE-003 | B88: Angenta | C88: Flupentixol + Melitracen | D88: Tablet | E88: Neuro / Anti-anxiety | F88: =(Table1[[#This Row],[Unit Price]] * 0.9) * Table1[[#This Row],[Pcs per Box]] -> 450 | G88: 100 | H88: =Table1[[#This Row],[Cost Price]]/Table1[[#This Row],[Pcs per Box]] -> 4.5 | I88: 5 | J88: =SUMIF('Stock In'!C:C, Table1[[#This Row],[Medicine ID]], 'Stock In'!E:E) * Table1[[#This Row],[Pcs per Box]] -> 300 | K88: =SUMIF('Sales Log Table'!C:C, Table1[[#This Row],[Medicine ID]], 'Sales Log Table'!E:E) -> 0 | L88: =Table1[[#This Row],[Total Received]] - Table1[[#This Row],[Total Sold]] -> 300 | M88: 50 | N88: 46563 | O88: =IF(Table1[[#This Row],[Current Stock]] <= Table1[[#This Row],[Min Stock]], "REORDER NOW", "Good") -> Good | P88: =(Table1[[#This Row],[Unit Price]] - Table1[[#This Row],[Cost Per Pc]]) * Table1[[#This Row],[Total Sold]] -> 0 | R88: =(Table1[[#This Row],[Total Received]] / Table1[[#This Row],[Pcs per Box]]) * Table1[[#This Row],[Cost Price]] -> 1350 | S88: =SUM($R$3:Table1[[#This Row],[Annual Consumption Value]]) / SUM(Table1[Annual Consumption Value]) -> 0.78861004 | T88: =IF(Table1[[#This Row],[Cumulative %]]<=0.8, "A", IF(Table1[[#This Row],[Cumulative %]]<=0.95, "B", "C")) -> A
A89: NE-004 | B89: Benzit | C89: Flupentixol + Melitracen | D89: Tablet | E89: Neuro / Anti-anxiety | F89: =(Table1[[#This Row],[Unit Price]] * 0.9) * Table1[[#This Row],[Pcs per Box]] -> 450 | G89: 100 | H89: =Table1[[#This Row],[Cost Price]]/Table1[[#This Row],[Pcs per Box]] -> 4.5 | I89: 5 | J89: =SUMIF('Stock In'!C:C, Table1[[#This Row],[Medicine ID]], 'Stock In'!E:E) * Table1[[#This Row],[Pcs per Box]] -> 100 | K89: =SUMIF('Sales Log Table'!C:C, Table1[[#This Row],[Medicine ID]], 'Sales Log Table'!E:E) -> 10 | L89: =Table1[[#This Row],[Total Received]] - Table1[[#This Row],[Total Sold]] -> 90 | M89: 50 | N89: 46563 | O89: =IF(Table1[[#This Row],[Current Stock]] <= Table1[[#This Row],[Min Stock]], "REORDER NOW", "Good") -> Good | P89: =(Table1[[#This Row],[Unit Price]] - Table1[[#This Row],[Cost Per Pc]]) * Table1[[#This Row],[Total Sold]] -> 5 | R89: =(Table1[[#This Row],[Total Received]] / Table1[[#This Row],[Pcs per Box]]) * Table1[[#This Row],[Cost Price]] -> 450 | S89: =SUM($R$3:Table1[[#This Row],[Annual Consumption Value]]) / SUM(Table1[Annual Consumption Value]) -> 0.79026246 | T89: =IF(Table1[[#This Row],[Cumulative %]]<=0.8, "A", IF(Table1[[#This Row],[Cumulative %]]<=0.95, "B", "C")) -> A
A90: NE-005 | B90: Melixol | C90: Flupentixol + Melitracen | D90: Tablet | E90: Neuro / Anti-anxiety | F90: =(Table1[[#This Row],[Unit Price]] * 0.9) * Table1[[#This Row],[Pcs per Box]] -> 225.9 | G90: 50 | H90: =Table1[[#This Row],[Cost Price]]/Table1[[#This Row],[Pcs per Box]] -> 4.518 | I90: 5.02 | J90: =SUMIF('Stock In'!C:C, Table1[[#This Row],[Medicine ID]], 'Stock In'!E:E) * Table1[[#This Row],[Pcs per Box]] -> 100 | K90: =SUMIF('Sales Log Table'!C:C, Table1[[#This Row],[Medicine ID]], 'Sales Log Table'!E:E) -> 0 | L90: =Table1[[#This Row],[Total Received]] - Table1[[#This Row],[Total Sold]] -> 100 | M90: 40 | N90: 46563 | O90: =IF(Table1[[#This Row],[Current Stock]] <= Table1[[#This Row],[Min Stock]], "REORDER NOW", "Good") -> Good | P90: =(Table1[[#This Row],[Unit Price]] - Table1[[#This Row],[Cost Per Pc]]) * Table1[[#This Row],[Total Sold]] -> 0 | R90: =(Table1[[#This Row],[Total Received]] / Table1[[#This Row],[Pcs per Box]]) * Table1[[#This Row],[Cost Price]] -> 451.8 | S90: =SUM($R$3:Table1[[#This Row],[Annual Consumption Value]]) / SUM(Table1[Annual Consumption Value]) -> 0.79192148 | T90: =IF(Table1[[#This Row],[Cumulative %]]<=0.8, "A", IF(Table1[[#This Row],[Cumulative %]]<=0.95, "B", "C")) -> A
A91: NE-006 | B91: Sensit | C91: Flupentixol + Melitracen | D91: Tablet | E91: Neuro / Anti-anxiety | F91: =(Table1[[#This Row],[Unit Price]] * 0.9) * Table1[[#This Row],[Pcs per Box]] -> 225 | G91: 50 | H91: =Table1[[#This Row],[Cost Price]]/Table1[[#This Row],[Pcs per Box]] -> 4.5 | I91: 5 | J91: =SUMIF('Stock In'!C:C, Table1[[#This Row],[Medicine ID]], 'Stock In'!E:E) * Table1[[#This Row],[Pcs per Box]] -> 50 | K91: =SUMIF('Sales Log Table'!C:C, Table1[[#This Row],[Medicine ID]], 'Sales Log Table'!E:E) -> 0 | L91: =Table1[[#This Row],[Total Received]] - Table1[[#This Row],[Total Sold]] -> 50 | M91: 20 | N91: 46563 | O91: =IF(Table1[[#This Row],[Current Stock]] <= Table1[[#This Row],[Min Stock]], "REORDER NOW", "Good") -> Good | P91: =(Table1[[#This Row],[Unit Price]] - Table1[[#This Row],[Cost Per Pc]]) * Table1[[#This Row],[Total Sold]] -> 0 | R91: =(Table1[[#This Row],[Total Received]] / Table1[[#This Row],[Pcs per Box]]) * Table1[[#This Row],[Cost Price]] -> 225 | S91: =SUM($R$3:Table1[[#This Row],[Annual Consumption Value]]) / SUM(Table1[Annual Consumption Value]) -> 0.79274769 | T91: =IF(Table1[[#This Row],[Cumulative %]]<=0.8, "A", IF(Table1[[#This Row],[Cumulative %]]<=0.95, "B", "C")) -> A
A92: NE-007 | B92: Unzip | C92: Flupentixol + Melitracen | D92: Tablet | E92: Neuro / Anti-anxiety | F92: =(Table1[[#This Row],[Unit Price]] * 0.9) * Table1[[#This Row],[Pcs per Box]] -> 225 | G92: 50 | H92: =Table1[[#This Row],[Cost Price]]/Table1[[#This Row],[Pcs per Box]] -> 4.5 | I92: 5 | J92: =SUMIF('Stock In'!C:C, Table1[[#This Row],[Medicine ID]], 'Stock In'!E:E) * Table1[[#This Row],[Pcs per Box]] -> 100 | K92: =SUMIF('Sales Log Table'!C:C, Table1[[#This Row],[Medicine ID]], 'Sales Log Table'!E:E) -> 0 | L92: =Table1[[#This Row],[Total Received]] - Table1[[#This Row],[Total Sold]] -> 100 | M92: 20 | N92: 46563 | O92: =IF(Table1[[#This Row],[Current Stock]] <= Table1[[#This Row],[Min Stock]], "REORDER NOW", "Good") -> Good | P92: =(Table1[[#This Row],[Unit Price]] - Table1[[#This Row],[Cost Per Pc]]) * Table1[[#This Row],[Total Sold]] -> 0 | R92: =(Table1[[#This Row],[Total Received]] / Table1[[#This Row],[Pcs per Box]]) * Table1[[#This Row],[Cost Price]] -> 450 | S92: =SUM($R$3:Table1[[#This Row],[Annual Consumption Value]]) / SUM(Table1[Annual Consumption Value]) -> 0.7944001 | T92: =IF(Table1[[#This Row],[Cumulative %]]<=0.8, "A", IF(Table1[[#This Row],[Cumulative %]]<=0.95, "B", "C")) -> A
A93: NE-008 | B93: Fluver 5 | C93: Flunarizine | D93: Tablet | E93: Common Migraine, (PVD) | F93: =(Table1[[#This Row],[Unit Price]] * 0.9) * Table1[[#This Row],[Pcs per Box]] -> 360 | G93: 100 | H93: =Table1[[#This Row],[Cost Price]]/Table1[[#This Row],[Pcs per Box]] -> 3.6 | I93: 4 | J93: =SUMIF('Stock In'!C:C, Table1[[#This Row],[Medicine ID]], 'Stock In'!E:E) * Table1[[#This Row],[Pcs per Box]] -> 300 | K93: =SUMIF('Sales Log Table'!C:C, Table1[[#This Row],[Medicine ID]], 'Sales Log Table'!E:E) -> 0 | L93: =Table1[[#This Row],[Total Received]] - Table1[[#This Row],[Total Sold]] -> 300 | N93: 46563 | O93: =IF(Table1[[#This Row],[Current Stock]] <= Table1[[#This Row],[Min Stock]], "REORDER NOW", "Good") -> Good | P93: =(Table1[[#This Row],[Unit Price]] - Table1[[#This Row],[Cost Per Pc]]) * Table1[[#This Row],[Total Sold]] -> 0 | R93: =(Table1[[#This Row],[Total Received]] / Table1[[#This Row],[Pcs per Box]]) * Table1[[#This Row],[Cost Price]] -> 1080 | S93: =SUM($R$3:Table1[[#This Row],[Annual Consumption Value]]) / SUM(Table1[Annual Consumption Value]) -> 0.79836589 | T93: =IF(Table1[[#This Row],[Cumulative %]]<=0.8, "A", IF(Table1[[#This Row],[Cumulative %]]<=0.95, "B", "C")) -> A
A94: NE-009 | B94: Fluver 10 | C94: Flunarizine | D94: Tablet | E94: Common Migraine, (PVD) | F94: =(Table1[[#This Row],[Unit Price]] * 0.9) * Table1[[#This Row],[Pcs per Box]] -> 630 | G94: 100 | H94: =Table1[[#This Row],[Cost Price]]/Table1[[#This Row],[Pcs per Box]] -> 6.3 | I94: 7 | J94: =SUMIF('Stock In'!C:C, Table1[[#This Row],[Medicine ID]], 'Stock In'!E:E) * Table1[[#This Row],[Pcs per Box]] -> 100 | K94: =SUMIF('Sales Log Table'!C:C, Table1[[#This Row],[Medicine ID]], 'Sales Log Table'!E:E) -> 0 | L94: =Table1[[#This Row],[Total Received]] - Table1[[#This Row],[Total Sold]] -> 100 | M94: 20 | N94: 46563 | O94: =IF(Table1[[#This Row],[Current Stock]] <= Table1[[#This Row],[Min Stock]], "REORDER NOW", "Good") -> Good | P94: =(Table1[[#This Row],[Unit Price]] - Table1[[#This Row],[Cost Per Pc]]) * Table1[[#This Row],[Total Sold]] -> 0 | R94: =(Table1[[#This Row],[Total Received]] / Table1[[#This Row],[Pcs per Box]]) * Table1[[#This Row],[Cost Price]] -> 630 | S94: =SUM($R$3:Table1[[#This Row],[Annual Consumption Value]]) / SUM(Table1[Annual Consumption Value]) -> 0.80067927 | T94: =IF(Table1[[#This Row],[Cumulative %]]<=0.8, "A", IF(Table1[[#This Row],[Cumulative %]]<=0.95, "B", "C")) -> B
A95: NE-010 | B95: Norium 10 | C95: Flunarizine | D95: Tablet | E95: Common Migraine, (PVD) | F95: 369.62 | G95: 60 | H95: =Table1[[#This Row],[Cost Price]]/Table1[[#This Row],[Pcs per Box]] -> 6.1603333 | I95: 7 | J95: =SUMIF('Stock In'!C:C, Table1[[#This Row],[Medicine ID]], 'Stock In'!E:E) * Table1[[#This Row],[Pcs per Box]] -> 180 | K95: =SUMIF('Sales Log Table'!C:C, Table1[[#This Row],[Medicine ID]], 'Sales Log Table'!E:E) -> 0 | L95: =Table1[[#This Row],[Total Received]] - Table1[[#This Row],[Total Sold]] -> 180 | M95: 60 | N95: 46563 | O95: =IF(Table1[[#This Row],[Current Stock]] <= Table1[[#This Row],[Min Stock]], "REORDER NOW", "Good") -> Good | P95: =(Table1[[#This Row],[Unit Price]] - Table1[[#This Row],[Cost Per Pc]]) * Table1[[#This Row],[Total Sold]] -> 0 | R95: =(Table1[[#This Row],[Total Received]] / Table1[[#This Row],[Pcs per Box]]) * Table1[[#This Row],[Cost Price]] -> 1108.86 | S95: =SUM($R$3:Table1[[#This Row],[Annual Consumption Value]]) / SUM(Table1[Annual Consumption Value]) -> 0.80475104 | T95: =IF(Table1[[#This Row],[Cumulative %]]<=0.8, "A", IF(Table1[[#This Row],[Cumulative %]]<=0.95, "B", "C")) -> B
A96: NE-011 | B96: Norium 5 | C96: Flunarizine | D96: Tablet | E96: Common Migraine, (PVD) | F96: 352.02 | G96: 100 | H96: =Table1[[#This Row],[Cost Price]]/Table1[[#This Row],[Pcs per Box]] -> 3.5202 | I96: 4 | J96: =SUMIF('Stock In'!C:C, Table1[[#This Row],[Medicine ID]], 'Stock In'!E:E) * Table1[[#This Row],[Pcs per Box]] -> 100 | K96: =SUMIF('Sales Log Table'!C:C, Table1[[#This Row],[Medicine ID]], 'Sales Log Table'!E:E) -> 0 | L96: =Table1[[#This Row],[Total Received]] - Table1[[#This Row],[Total Sold]] -> 100 | M96: 20 | N96: 46563 | O96: =IF(Table1[[#This Row],[Current Stock]] <= Table1[[#This Row],[Min Stock]], "REORDER NOW", "Good") -> Good | P96: =(Table1[[#This Row],[Unit Price]] - Table1[[#This Row],[Cost Per Pc]]) * Table1[[#This Row],[Total Sold]] -> 0 | R96: =(Table1[[#This Row],[Total Received]] / Table1[[#This Row],[Pcs per Box]]) * Table1[[#This Row],[Cost Price]] -> 352.02 | S96: =SUM($R$3:Table1[[#This Row],[Annual Consumption Value]]) / SUM(Table1[Annual Consumption Value]) -> 0.80604367 | T96: =IF(Table1[[#This Row],[Cumulative %]]<=0.8, "A", IF(Table1[[#This Row],[Cumulative %]]<=0.95, "B", "C")) -> B
A97: PA-001 | B97: Napa | C97: Paracetamol | D97: Tablet | E97: Fever, Pain Relief | F97: =(Table1[[#This Row],[Unit Price]] * 0.9) * Table1[[#This Row],[Pcs per Box]] -> 550.8 | G97: 510 | H97: =Table1[[#This Row],[Cost Price]]/Table1[[#This Row],[Pcs per Box]] -> 1.08 | I97: 1.2 | J97: =SUMIF('Stock In'!C:C, Table1[[#This Row],[Medicine ID]], 'Stock In'!E:E) * Table1[[#This Row],[Pcs per Box]] -> 2040 | K97: =SUMIF('Sales Log Table'!C:C, Table1[[#This Row],[Medicine ID]], 'Sales Log Table'!E:E) -> 30 | L97: =Table1[[#This Row],[Total Received]] - Table1[[#This Row],[Total Sold]] -> 2010 | M97: 450 | N97: 46563 | O97: =IF(Table1[[#This Row],[Current Stock]] <= Table1[[#This Row],[Min Stock]], "REORDER NOW", "Good") -> Good | P97: =(Table1[[#This Row],[Unit Price]] - Table1[[#This Row],[Cost Per Pc]]) * Table1[[#This Row],[Total Sold]] -> 3.6 | R97: =(Table1[[#This Row],[Total Received]] / Table1[[#This Row],[Pcs per Box]]) * Table1[[#This Row],[Cost Price]] -> 2203.2 | S97: =SUM($R$3:Table1[[#This Row],[Annual Consumption Value]]) / SUM(Table1[Annual Consumption Value]) -> 0.81413389 | T97: =IF(Table1[[#This Row],[Cumulative %]]<=0.8, "A", IF(Table1[[#This Row],[Cumulative %]]<=0.95, "B", "C")) -> B
A98: PA-002 | B98: Napa Extra | C98: Paracetamol + Caffeine | D98: Tablet | E98: Fever, Pain Relief | F98: =(Table1[[#This Row],[Unit Price]] * 0.9) * Table1[[#This Row],[Pcs per Box]] -> 297 | G98: 132 | H98: =Table1[[#This Row],[Cost Price]]/Table1[[#This Row],[Pcs per Box]] -> 2.25 | I98: 2.5 | J98: =SUMIF('Stock In'!C:C, Table1[[#This Row],[Medicine ID]], 'Stock In'!E:E) * Table1[[#This Row],[Pcs per Box]] -> 264 | K98: =SUMIF('Sales Log Table'!C:C, Table1[[#This Row],[Medicine ID]], 'Sales Log Table'!E:E) -> 10 | L98: =Table1[[#This Row],[Total Received]] - Table1[[#This Row],[Total Sold]] -> 254 | M98: 60 | N98: 46563 | O98: =IF(Table1[[#This Row],[Current Stock]] <= Table1[[#This Row],[Min Stock]], "REORDER NOW", "Good") -> Good | P98: =(Table1[[#This Row],[Unit Price]] - Table1[[#This Row],[Cost Per Pc]]) * Table1[[#This Row],[Total Sold]] -> 2.5 | R98: =(Table1[[#This Row],[Total Received]] / Table1[[#This Row],[Pcs per Box]]) * Table1[[#This Row],[Cost Price]] -> 594 | S98: =SUM($R$3:Table1[[#This Row],[Annual Consumption Value]]) / SUM(Table1[Annual Consumption Value]) -> 0.81631508 | T98: =IF(Table1[[#This Row],[Cumulative %]]<=0.8, "A", IF(Table1[[#This Row],[Cumulative %]]<=0.95, "B", "C")) -> B
A99: PA-003 | B99: Napa Rapid | C99: Paracetamol | D99: Tablet | E99: Fever | F99: =(Table1[[#This Row],[Unit Price]] * 0.9) * Table1[[#This Row],[Pcs per Box]] -> 315.9 | G99: 270 | H99: =Table1[[#This Row],[Cost Price]]/Table1[[#This Row],[Pcs per Box]] -> 1.17 | I99: 1.3 | J99: =SUMIF('Stock In'!C:C, Table1[[#This Row],[Medicine ID]], 'Stock In'!E:E) * Table1[[#This Row],[Pcs per Box]] -> 1080 | K99: =SUMIF('Sales Log Table'!C:C, Table1[[#This Row],[Medicine ID]], 'Sales Log Table'!E:E) -> 0 | L99: =Table1[[#This Row],[Total Received]] - Table1[[#This Row],[Total Sold]] -> 1080 | M99: 200 | N99: 46563 | O99: =IF(Table1[[#This Row],[Current Stock]] <= Table1[[#This Row],[Min Stock]], "REORDER NOW", "Good") -> Good | P99: =(Table1[[#This Row],[Unit Price]] - Table1[[#This Row],[Cost Per Pc]]) * Table1[[#This Row],[Total Sold]] -> 0 | R99: =(Table1[[#This Row],[Total Received]] / Table1[[#This Row],[Pcs per Box]]) * Table1[[#This Row],[Cost Price]] -> 1263.6 | S99: =SUM($R$3:Table1[[#This Row],[Annual Consumption Value]]) / SUM(Table1[Annual Consumption Value]) -> 0.82095506 | T99: =IF(Table1[[#This Row],[Cumulative %]]<=0.8, "A", IF(Table1[[#This Row],[Cumulative %]]<=0.95, "B", "C")) -> B
A100: PA-004 | B100: Napa Extend | C100: Paracetamol | D100: Tablet | E100: Headache, Feverishness | F100: =(Table1[[#This Row],[Unit Price]] * 0.9) * Table1[[#This Row],[Pcs per Box]] -> 259.2 | G100: 144 | H100: =Table1[[#This Row],[Cost Price]]/Table1[[#This Row],[Pcs per Box]] -> 1.8 | I100: 2 | J100: =SUMIF('Stock In'!C:C, Table1[[#This Row],[Medicine ID]], 'Stock In'!E:E) * Table1[[#This Row],[Pcs per Box]] -> 864 | K100: =SUMIF('Sales Log Table'!C:C, Table1[[#This Row],[Medicine ID]], 'Sales Log Table'!E:E) -> 0 | L100: =Table1[[#This Row],[Total Received]] - Table1[[#This Row],[Total Sold]] -> 864 | M100: 700 | N100: 46563 | O100: =IF(Table1[[#This Row],[Current Stock]] <= Table1[[#This Row],[Min Stock]], "REORDER NOW", "Good") -> Good | P100: =(Table1[[#This Row],[Unit Price]] - Table1[[#This Row],[Cost Per Pc]]) * Table1[[#This Row],[Total Sold]] -> 0 | R100: =(Table1[[#This Row],[Total Received]] / Table1[[#This Row],[Pcs per Box]]) * Table1[[#This Row],[Cost Price]] -> 1555.2 | S100: =SUM($R$3:Table1[[#This Row],[Annual Consumption Value]]) / SUM(Table1[Annual Consumption Value]) -> 0.8266658 | T100: =IF(Table1[[#This Row],[Cumulative %]]<=0.8, "A", IF(Table1[[#This Row],[Cumulative %]]<=0.95, "B", "C")) -> B
...

Sheet Sales Log Table
A1: DAILY SALES LOG
A2: invoice ID | B2: Date | C2: Medicine ID | D2: Medicine Name | E2: Qty Sold | F2: Total Price | G2: Payment Method
A3: INV-260517-01 | B3: 17-05-2026 | C3: =_xlfn.XLOOKUP(Table4[[#This Row],[Medicine Name]], 'Medicine Master Table'!B:B, 'Medicine Master Table'!A:A, "Not Found") -> PA-001 | D3: Napa | E3: 30 | F3: =_xlfn.XLOOKUP(Table4[[#This Row],[Medicine ID]], 'Medicine Master Table'!A:A, 'Medicine Master Table'!I:I, 0) * Table4[[#This Row],[Qty Sold]] -> 36 | G3: Cash
A4: INV-260517-01 | B4: 17-05-2026 | C4: =_xlfn.XLOOKUP(Table4[[#This Row],[Medicine Name]], 'Medicine Master Table'!B:B, 'Medicine Master Table'!A:A, "Not Found") -> PA-002 | D4: Napa Extra | E4: 10 | F4: =_xlfn.XLOOKUP(Table4[[#This Row],[Medicine ID]], 'Medicine Master Table'!A:A, 'Medicine Master Table'!I:I, 0) * Table4[[#This Row],[Qty Sold]] -> 25 | G4: Cash
A5: INV-260524-01 | B5: 24-05-2026 | C5: =_xlfn.XLOOKUP(Table4[[#This Row],[Medicine Name]], 'Medicine Master Table'!B:B, 'Medicine Master Table'!A:A, "Not Found") -> NE-004 | D5: Benzit | E5: 10 | F5: =_xlfn.XLOOKUP(Table4[[#This Row],[Medicine ID]], 'Medicine Master Table'!A:A, 'Medicine Master Table'!I:I, 0) * Table4[[#This Row],[Qty Sold]] -> 50 | G5: Cash
A6: INV-260524-01 | B6: 24-05-2026 | C6: =_xlfn.XLOOKUP(Table4[[#This Row],[Medicine Name]], 'Medicine Master Table'!B:B, 'Medicine Master Table'!A:A, "Not Found") -> GA-004 | D6: Exium | E6: 10 | F6: =_xlfn.XLOOKUP(Table4[[#This Row],[Medicine ID]], 'Medicine Master Table'!A:A, 'Medicine Master Table'!I:I, 0) * Table4[[#This Row],[Qty Sold]] -> 90 | G6: Cash
A7: INV-260524-01 | B7: 24-05-2026 | C7: =_xlfn.XLOOKUP(Table4[[#This Row],[Medicine Name]], 'Medicine Master Table'!B:B, 'Medicine Master Table'!A:A, "Not Found") -> GA-003 | D7: Seclo | E7: 10 | F7: =_xlfn.XLOOKUP(Table4[[#This Row],[Medicine ID]], 'Medicine Master Table'!A:A, 'Medicine Master Table'!I:I, 0) * Table4[[#This Row],[Qty Sold]] -> 60 | G7: Cash
A8: INV-260524-01 | B8: 24-05-2026 | C8: =_xlfn.XLOOKUP(Table4[[#This Row],[Medicine Name]], 'Medicine Master Table'!B:B, 'Medicine Master Table'!A:A, "Not Found") -> AL-016 | D8: Bilbest 20mg | E8: 10 | F8: =_xlfn.XLOOKUP(Table4[[#This Row],[Medicine ID]], 'Medicine Master Table'!A:A, 'Medicine Master Table'!I:I, 0) * Table4[[#This Row],[Qty Sold]] -> 150 | G8: Cash
A9: INV-260524-01 | B9: 24-05-2026 | C9: =_xlfn.XLOOKUP(Table4[[#This Row],[Medicine Name]], 'Medicine Master Table'!B:B, 'Medicine Master Table'!A:A, "Not Found") -> NE-001 | D9: Anzet | E9: 10 | F9: =_xlfn.XLOOKUP(Table4[[#This Row],[Medicine ID]], 'Medicine Master Table'!A:A, 'Medicine Master Table'!I:I, 0) * Table4[[#This Row],[Qty Sold]] -> 50 | G9: Cash
A10: INV-260524-01 | B10: 24-05-2026 | C10: =_xlfn.XLOOKUP(Table4[[#This Row],[Medicine Name]], 'Medicine Master Table'!B:B, 'Medicine Master Table'!A:A, "Not Found") -> GA-005 | D10: Maxpro 20mg | E10: 14 | F10: =_xlfn.XLOOKUP(Table4[[#This Row],[Medicine ID]], 'Medicine Master Table'!A:A, 'Medicine Master Table'!I:I, 0) * Table4[[#This Row],[Qty Sold]] -> 98 | G10: Cash
A11: INV-260524-01 | B11: 24-05-2026 | C11: =_xlfn.XLOOKUP(Table4[[#This Row],[Medicine Name]], 'Medicine Master Table'!B:B, 'Medicine Master Table'!A:A, "Not Found") -> AL-005 | D11: Alatrol | E11: 10 | F11: =_xlfn.XLOOKUP(Table4[[#This Row],[Medicine ID]], 'Medicine Master Table'!A:A, 'Medicine Master Table'!I:I, 0) * Table4[[#This Row],[Qty Sold]] -> 30 | G11: Cash
A12: INV-260524-01 | B12: 24-05-2026 | C12: =_xlfn.XLOOKUP(Table4[[#This Row],[Medicine Name]], 'Medicine Master Table'!B:B, 'Medicine Master Table'!A:A, "Not Found") -> AN-005 | D12: Zimax 500 | E12: 3 | F12: =_xlfn.XLOOKUP(Table4[[#This Row],[Medicine ID]], 'Medicine Master Table'!A:A, 'Medicine Master Table'!I:I, 0) * Table4[[#This Row],[Qty Sold]] -> 120 | G12: Cash
A13: INV-260524-02 | B13: 24-05-2026 | C13: =_xlfn.XLOOKUP(Table4[[#This Row],[Medicine Name]], 'Medicine Master Table'!B:B, 'Medicine Master Table'!A:A, "Not Found") -> AL-015 | D13: Ebatin | E13: 10 | F13: =_xlfn.XLOOKUP(Table4[[#This Row],[Medicine ID]], 'Medicine Master Table'!A:A, 'Medicine Master Table'!I:I, 0) * Table4[[#This Row],[Qty Sold]] -> 100 | G13: Cash
A14: INV-260524-02 | B14: 24-05-2026 | C14: =_xlfn.XLOOKUP(Table4[[#This Row],[Medicine Name]], 'Medicine Master Table'!B:B, 'Medicine Master Table'!A:A, "Not Found") -> GA-003 | D14: Seclo | E14: 10 | F14: =_xlfn.XLOOKUP(Table4[[#This Row],[Medicine ID]], 'Medicine Master Table'!A:A, 'Medicine Master Table'!I:I, 0) * Table4[[#This Row],[Qty Sold]] -> 60 | G14: Cash
A15: INV-260524-03 | B15: 24-05-2026 | C15: =_xlfn.XLOOKUP(Table4[[#This Row],[Medicine Name]], 'Medicine Master Table'!B:B, 'Medicine Master Table'!A:A, "Not Found") -> CAL-007 | D15: Coralcin-D | E15: 50 | F15: =_xlfn.XLOOKUP(Table4[[#This Row],[Medicine ID]], 'Medicine Master Table'!A:A, 'Medicine Master Table'!I:I, 0) * Table4[[#This Row],[Qty Sold]] -> 550 | G15: Cash

Sheet Stock In
A1: INCOMING STOCK LOG
A2: Batch ID | B2: Date | C2: Medicine ID | D2: Medicine Name | E2: Qty Received | F2: Cost Price | G2: Supplier Name
A3: BCH-001 | B3: 16-05-2026 | C3: =_xlfn.XLOOKUP(Table5[[#This Row],[Medicine Name]], 'Medicine Master Table'!B:B, 'Medicine Master Table'!A:A, "Not Found") -> PA-001 | D3: Napa | E3: 4 | F3: =_xlfn.XLOOKUP(Table5[[#This Row],[Medicine ID]], 'Medicine Master Table'!A:A, 'Medicine Master Table'!F:F, 0) -> 550.8 | G3: Beximco Pharma
A4: BCH-002 | B4: 17-05-2026 | C4: =_xlfn.XLOOKUP(Table5[[#This Row],[Medicine Name]], 'Medicine Master Table'!B:B, 'Medicine Master Table'!A:A, "Not Found") -> PA-002 | D4: Napa Extra | E4: 2 | F4: =_xlfn.XLOOKUP(Table5[[#This Row],[Medicine ID]], 'Medicine Master Table'!A:A, 'Medicine Master Table'!F:F, 0) -> 297 | G4: Beximco Pharma
A5: BCH-003 | B5: 18-05-2026 | C5: =_xlfn.XLOOKUP(Table5[[#This Row],[Medicine Name]], 'Medicine Master Table'!B:B, 'Medicine Master Table'!A:A, "Not Found") -> PA-003 | D5: Napa Rapid | E5: 4 | F5: =_xlfn.XLOOKUP(Table5[[#This Row],[Medicine ID]], 'Medicine Master Table'!A:A, 'Medicine Master Table'!F:F, 0) -> 315.9 | G5: Beximco Pharma
A6: BCH-004 | B6: 19-05-2026 | C6: =_xlfn.XLOOKUP(Table5[[#This Row],[Medicine Name]], 'Medicine Master Table'!B:B, 'Medicine Master Table'!A:A, "Not Found") -> PA-004 | D6: Napa Extend | E6: 6 | F6: =_xlfn.XLOOKUP(Table5[[#This Row],[Medicine ID]], 'Medicine Master Table'!A:A, 'Medicine Master Table'!F:F, 0) -> 259.2 | G6: Beximco Pharma
A7: BCH-005 | B7: 19-05-2026 | C7: =_xlfn.XLOOKUP(Table5[[#This Row],[Medicine Name]], 'Medicine Master Table'!B:B, 'Medicine Master Table'!A:A, "Not Found") -> PA-005 | D7: Napa One | E7: 4 | F7: =_xlfn.XLOOKUP(Table5[[#This Row],[Medicine ID]], 'Medicine Master Table'!A:A, 'Medicine Master Table'!F:F, 0) -> 405 | G7: Beximco Pharma
A8: BCH-006 | B8: 19-05-2026 | C8: =_xlfn.XLOOKUP(Table5[[#This Row],[Medicine Name]], 'Medicine Master Table'!B:B, 'Medicine Master Table'!A:A, "Not Found") -> PA-006 | D8: Xpa | E8: 3 | F8: =_xlfn.XLOOKUP(Table5[[#This Row],[Medicine ID]], 'Medicine Master Table'!A:A, 'Medicine Master Table'!F:F, 0) -> 270 | G8: AristoPharma
A9: BCH-007 | B9: 19-05-2026 | C9: =_xlfn.XLOOKUP(Table5[[#This Row],[Medicine Name]], 'Medicine Master Table'!B:B, 'Medicine Master Table'!A:A, "Not Found") -> PA-007 | D9: Xpa XR | E9: 7 | F9: =_xlfn.XLOOKUP(Table5[[#This Row],[Medicine ID]], 'Medicine Master Table'!A:A, 'Medicine Master Table'!F:F, 0) -> 360 | G9: AristoPharma
A10: BCH-008 | B10: 19-05-2026 | C10: =_xlfn.XLOOKUP(Table5[[#This Row],[Medicine Name]], 'Medicine Master Table'!B:B, 'Medicine Master Table'!A:A, "Not Found") -> PA-008 | D10: Ace | E10: 8 | F10: =_xlfn.XLOOKUP(Table5[[#This Row],[Medicine ID]], 'Medicine Master Table'!A:A, 'Medicine Master Table'!F:F, 0) -> 540 | G10: Square Pharma
A11: BCH-009 | B11: 19-05-2026 | C11: =_xlfn.XLOOKUP(Table5[[#This Row],[Medicine Name]], 'Medicine Master Table'!B:B, 'Medicine Master Table'!A:A, "Not Found") -> PA-009 | D11: Ace Plus | E11: 3 | F11: =_xlfn.XLOOKUP(Table5[[#This Row],[Medicine ID]], 'Medicine Master Table'!A:A, 'Medicine Master Table'!F:F, 0) -> 451.8 | G11: Square Pharma
A12: BCH-010 | B12: 19-05-2026 | C12: =_xlfn.XLOOKUP(Table5[[#This Row],[Medicine Name]], 'Medicine Master Table'!B:B, 'Medicine Master Table'!A:A, "Not Found") -> PA-010 | D12: Ace Power | E12: 1 | F12: =_xlfn.XLOOKUP(Table5[[#This Row],[Medicine ID]], 'Medicine Master Table'!A:A, 'Medicine Master Table'!F:F, 0) -> 405 | G12: Square Pharma
A13: BCH-011 | B13: 19-05-2026 | C13: =_xlfn.XLOOKUP(Table5[[#This Row],[Medicine Name]], 'Medicine Master Table'!B:B, 'Medicine Master Table'!A:A, "Not Found") -> GA-001 | D13: Losectil 20 | E13: 6 | F13: =_xlfn.XLOOKUP(Table5[[#This Row],[Medicine ID]], 'Medicine Master Table'!A:A, 'Medicine Master Table'!F:F, 0) -> 1584.1 | G13: Eskayef Pharma
A14: BCH-012 | B14: 19-05-2026 | C14: =_xlfn.XLOOKUP(Table5[[#This Row],[Medicine Name]], 'Medicine Master Table'!B:B, 'Medicine Master Table'!A:A, "Not Found") -> GA-002 | D14: Losectil 40 | E14: 5 | F14: =_xlfn.XLOOKUP(Table5[[#This Row],[Medicine ID]], 'Medicine Master Table'!A:A, 'Medicine Master Table'!F:F, 0) -> 352.02 | G14: Square Pharma
... A124: BCH-123 | B124: 23-05-2026 | C124: =_xlfn.XLOOKUP(Table5[[#This Row],[Medicine Name]], 'Medicine Master Table'!B:B, 'Medicine Master Table'!A:A, "Not Found") -> AL-001 | D124: Fenadin 120mg | E124: 5 | F124: =_xlfn.XLOOKUP(Table5[[#This Row],[Medicine ID]], 'Medicine Master Table'!A:A, 'Medicine Master Table'!F:F, 0) -> 396.23 | G124: Renata Pharma
